{
  "category_id": 150573,
  "category_name": "Büyük Beden Spor Tayt",
  "total_products": 9,
  "scraped_at": "2025-12-28T21:40:35.865590",
  "products": [
    {
      "id": 1062638921,
      "name": "İçi Peluş Termal Tayt Battal Büyük Beden Kışlık Peluş Tayt",
      "inStock": true,
      "brand": {
        "id": 1440061,
        "name": "MODASFORM"
      },
      "webBrand": {
        "id": 1440061,
        "name": "MODASFORM"
      },
      "category": {
        "id": 0,
        "name": ""
      },
      "price": {
        "originalPrice": 699,
        "discountedPrice": 500,
        "oldPrice": 699,
        "sellingPrice": 500,
        "buyingPrice": 500,
        "rrp": 699,
        "pureRrp": 699,
        "favoritedPrice": 0,
        "currency": "TL",
        "originalPriceText": "699,00",
        "discountedPriceText": "500,00",
        "oldPriceText": "699,00",
        "sellingPriceText": "500,00",
        "buyingPriceText": "500,00",
        "rrpText": "699,00",
        "lowestPriceBadge": {
          "showBadge": true,
          "discountPercentage": 28,
          "showFlameIcon": false
        }
      },
      "images": [
        "https://cdn.dsmcdn.com/ty1797/prod/QC_PREP/20251207/12/01503187-9a54-37b2-8c44-61e46cc9ee89/1_org_zoom.jpg",
        "https://cdn.dsmcdn.com/ty1799/prod/QC_PREP/20251207/12/2c25703a-5b63-35b6-b524-d4d2d835d560/1_org_zoom.jpg",
        "https://cdn.dsmcdn.com/ty1797/prod/QC_PREP/20251207/12/3769dde0-e324-3628-a5e6-8f078cd8000d/1_org_zoom.jpg",
        "https://cdn.dsmcdn.com/ty1798/prod/QC_PREP/20251207/12/8b158f79-d63e-3237-b704-668fce9a5c5a/1_org_zoom.jpg"
      ],
      "imageUrl": "https://cdn.dsmcdn.com/ty1797/prod/QC_PREP/20251207/12/01503187-9a54-37b2-8c44-61e46cc9ee89/1_org_zoom.jpg",
      "merchantListings": [
        {
          "promotions": [
            {
              "name": "300 TL ve Üzeri Kargo Bedava (Satıcı Karşılar)",
              "promotionDiscountType": "Cargo",
              "shortName": "Kargo Bedava",
              "id": 23749532,
              "discountType": 7,
              "isApplied": true,
              "isTyPlus": false
            }
          ],
          "variants": [
            {
              "unitInfo": {
                "unitPrice": null,
                "typeName": null,
                "unit": null
              },
              "userSegment": null,
              "discountedPriceInfo": "",
              "listingId": "aabd54494de700d87577d44d608974c8",
              "barcode": "Ms-96",
              "groupTagIds": [],
              "variantAttributes": [
                {
                  "attributeName": "Beden",
                  "attributeValue": "L"
                }
              ],
              "tagDetails": [
                {
                  "tag": "kategori_encoksatanlar",
                  "displayName": "kategori_encoksatanlar",
                  "tagId": 1715,
                  "searchable": true,
                  "priceTagStamp": false,
                  "hasStamp": true
                },
                {
                  "tag": "turuncu_kampanya_urunu",
                  "displayName": "Çok Avantajlı Ürün",
                  "tagId": 4898,
                  "searchable": true,
                  "priceTagStamp": true,
                  "hasStamp": true
                },
                {
                  "tag": "lowest_price",
                  "displayName": "",
                  "tagId": 1,
                  "searchable": true,
                  "priceTagStamp": true,
                  "hasStamp": false
                },
                {
                  "tag": "lowest_price_duration_14",
                  "displayName": "Son 14 Günün En Düşük Fiyatı",
                  "tagId": 7590,
                  "searchable": true,
                  "priceTagStamp": true,
                  "hasStamp": true
                },
                {
                  "tag": "eventdeal",
                  "displayName": "",
                  "tagId": 1,
                  "searchable": false,
                  "priceTagStamp": true,
                  "hasStamp": false
                }
              ],
              "price": {
                "currency": "TRY",
                "buyingPrice": 0,
                "sellingPrice": 500,
                "originalPrice": 699,
                "discountedPrice": 500,
                "profitMargin": 0,
                "rrp": 0,
                "couponApplicablePrice": 500,
                "discountedPriceAfterNoLimitPromotions": 500,
                "tyPlusCouponApplicablePrice": 500
              },
              "rushDeliveryDuration": 0,
              "lowestPriceDuration": {
                "duration": 14
              },
              "itemNumber": 1469594117,
              "quantity": 988,
              "sellable": true,
              "isWinner": true,
              "freeCargo": true,
              "hasCollectable": true
            }
          ],
          "stamps": [],
          "customValues": [
            {
              "key": "deliveryCountries",
              "value": "AZ"
            }
          ],
          "merchant": {
            "id": 532317
          },
          "isWinner": true,
          "freeCargo": true
        }
      ],
      "recommendedRetailPrice": null,
      "isRunningOut": false,
      "url": "/modasform/ici-pelus-termal-tayt-battal-buyuk-beden-kislik-pelus-tayt-p-1062638921",
      "rating": {
        "averageRating": 4.857142857142857,
        "totalComments": 7
      },
      "ratingScore": {
        "averageRating": 4.857142857142857,
        "totalCount": 7
      },
      "hasReviewPhoto": true,
      "stamps": [],
      "tagDetails": [
        {
          "tag": "kategori_encoksatanlar",
          "displayName": "kategori_encoksatanlar",
          "tagId": 1715,
          "searchable": true,
          "priceTagStamp": false,
          "hasStamp": true
        },
        {
          "tag": "turuncu_kampanya_urunu",
          "displayName": "Çok Avantajlı Ürün",
          "tagId": 4898,
          "searchable": true,
          "priceTagStamp": true,
          "hasStamp": true
        },
        {
          "tag": "lowest_price",
          "displayName": "",
          "tagId": 1,
          "searchable": true,
          "priceTagStamp": true,
          "hasStamp": false
        },
        {
          "tag": "lowest_price_duration_14",
          "displayName": "Son 14 Günün En Düşük Fiyatı",
          "tagId": 7590,
          "searchable": true,
          "priceTagStamp": true,
          "hasStamp": true
        },
        {
          "tag": "eventdeal",
          "displayName": "",
          "tagId": 1,
          "searchable": false,
          "priceTagStamp": true,
          "hasStamp": false
        }
      ],
      "promotions": [
        {
          "id": 23749532,
          "name": "300 TL ve Üzeri Kargo Bedava (Satıcı Karşılar)",
          "discountType": 7,
          "shortName": "Kargo Bedava",
          "promotionDiscountType": "Cargo",
          "isTyPlus": false
        }
      ],
      "pricePromotion": null,
      "socialProofs": [
        {
          "type": "pageViewCount",
          "value": "452",
          "translateKey": "socialProof_pageViewCount",
          "icon": "https://cdn.dsmcdn.com/mobile/search-result/Socialproof_pageviewcount.png"
        },
        {
          "type": "basketCount",
          "value": "362",
          "translateKey": "socialProof_basketCount",
          "icon": "https://cdn.dsmcdn.com/mobile/search-result/Socialproof_basketcount.png"
        },
        {
          "type": "orderCountL3D",
          "value": "65",
          "translateKey": "socialProof_orderCountL365D",
          "icon": "https://cdn.dsmcdn.com/web/production/rocket-icon.png"
        },
        {
          "type": "favoriteCount",
          "value": "753",
          "translateKey": "socialProof_favoriteCount",
          "icon": "https://cdn.dsmcdn.com/web/production/orange-heart.png"
        }
      ],
      "lowestPriceDuration": 14,
      "stripBadge": {
        "label": "popular",
        "backgroundColor": "#BB0000",
        "textColor": "#FFFFFF"
      },
      "winnerVariant": {
        "unitInfo": {
          "unitPrice": null,
          "typeName": null,
          "unit": null
        },
        "userSegment": null,
        "discountedPriceInfo": "",
        "listingId": "aabd54494de700d87577d44d608974c8",
        "barcode": "Ms-96",
        "groupTagIds": [],
        "variantAttributes": [
          {
            "attributeName": "Beden",
            "attributeValue": "L"
          }
        ],
        "tagDetails": [
          {
            "tag": "kategori_encoksatanlar",
            "displayName": "kategori_encoksatanlar",
            "tagId": 1715,
            "searchable": true,
            "priceTagStamp": false,
            "hasStamp": true
          },
          {
            "tag": "turuncu_kampanya_urunu",
            "displayName": "Çok Avantajlı Ürün",
            "tagId": 4898,
            "searchable": true,
            "priceTagStamp": true,
            "hasStamp": true
          },
          {
            "tag": "lowest_price",
            "displayName": "",
            "tagId": 1,
            "searchable": true,
            "priceTagStamp": true,
            "hasStamp": false
          },
          {
            "tag": "lowest_price_duration_14",
            "displayName": "Son 14 Günün En Düşük Fiyatı",
            "tagId": 7590,
            "searchable": true,
            "priceTagStamp": true,
            "hasStamp": true
          },
          {
            "tag": "eventdeal",
            "displayName": "",
            "tagId": 1,
            "searchable": false,
            "priceTagStamp": true,
            "hasStamp": false
          }
        ],
        "price": {
          "currency": "TRY",
          "buyingPrice": 0,
          "sellingPrice": 500,
          "originalPrice": 699,
          "discountedPrice": 500,
          "profitMargin": 0,
          "rrp": 0,
          "couponApplicablePrice": 500,
          "discountedPriceAfterNoLimitPromotions": 500,
          "tyPlusCouponApplicablePrice": 500
        },
        "rushDeliveryDuration": 0,
        "lowestPriceDuration": {
          "duration": 14
        },
        "itemNumber": 1469594117,
        "quantity": 988,
        "sellable": true,
        "isWinner": true,
        "freeCargo": true,
        "hasCollectable": true
      },
      "priceChange": "NONE",
      "promotion": [
        {
          "id": 23749532,
          "name": "300 TL ve Üzeri Kargo Bedava (Satıcı Karşılar)",
          "discountType": 7,
          "shortName": "Kargo Bedava",
          "promotionDiscountType": "Cargo",
          "isTyPlus": false
        }
      ],
      "isFlash": false,
      "quantityStatusBadge": {
        "quantity": null,
        "badgeType": null
      }
    },
    {
      "id": 887042058,
      "name": "Kadın Dikişsiz Bileği Saran Özel Bant Iç Yüzeyi Peluşlu Büyük Beden Termal Tayt",
      "inStock": true,
      "brand": {
        "id": 1041874,
        "name": "Genel Markalar"
      },
      "webBrand": {
        "id": 1041874,
        "name": "Genel Markalar"
      },
      "category": {
        "id": 0,
        "name": ""
      },
      "price": {
        "originalPrice": 284.99,
        "discountedPrice": 284.99,
        "oldPrice": 0,
        "sellingPrice": 284.99,
        "buyingPrice": 284.99,
        "rrp": 284.99,
        "pureRrp": 284.99,
        "favoritedPrice": 0,
        "currency": "TL",
        "originalPriceText": "284,99",
        "discountedPriceText": "284,99",
        "oldPriceText": "0,00",
        "sellingPriceText": "284,99",
        "buyingPriceText": "284,99",
        "rrpText": "284,99"
      },
      "images": [
        "https://cdn.dsmcdn.com/ty1619/prod/QC/20241225/15/45da6708-a931-326f-b661-3e11200f2bc2/1_org_zoom.jpg",
        "https://cdn.dsmcdn.com/ty1618/prod/QC/20241225/15/28264d12-d221-3371-bc47-58310e8eec84/1_org_zoom.jpg",
        "https://cdn.dsmcdn.com/ty1618/prod/QC/20241225/15/d89a1731-f47e-310c-b2dc-9c0e7a6badc6/1_org_zoom.jpg",
        "https://cdn.dsmcdn.com/ty1618/prod/QC/20241225/15/85c6230a-13e0-3dcb-aaf8-04cf09ff358a/1_org_zoom.jpg"
      ],
      "imageUrl": "https://cdn.dsmcdn.com/ty1619/prod/QC/20241225/15/45da6708-a931-326f-b661-3e11200f2bc2/1_org_zoom.jpg",
      "merchantListings": [
        {
          "promotions": [
            {
              "name": "300 TL ve Üzeri Kargo Bedava (Satıcı Karşılar)",
              "promotionDiscountType": "Cargo",
              "shortName": "Kargo Bedava",
              "id": 25475568,
              "discountType": 7,
              "isApplied": false,
              "isTyPlus": false
            }
          ],
          "variants": [
            {
              "unitInfo": {
                "unitPrice": null,
                "typeName": null,
                "unit": null
              },
              "userSegment": null,
              "discountedPriceInfo": "",
              "listingId": "55212ebb9b2725ce484fcbc46115ae1d",
              "barcode": "TYBXL9AXT7SEK25071",
              "groupTagIds": [],
              "variantAttributes": [
                {
                  "attributeName": "Beden",
                  "attributeValue": "2XL"
                }
              ],
              "tagDetails": [
                {
                  "tag": "turuncu_kampanya_urunu",
                  "displayName": "Çok Avantajlı Ürün",
                  "tagId": 4898,
                  "searchable": true,
                  "priceTagStamp": true,
                  "hasStamp": true
                },
                {
                  "tag": "eventdeal",
                  "displayName": "",
                  "tagId": 1,
                  "searchable": false,
                  "priceTagStamp": true,
                  "hasStamp": false
                }
              ],
              "price": {
                "currency": "TRY",
                "buyingPrice": 0,
                "sellingPrice": 284.99,
                "originalPrice": 284.99,
                "discountedPrice": 284.99,
                "profitMargin": 0,
                "rrp": 0,
                "couponApplicablePrice": 284.99,
                "discountedPriceAfterNoLimitPromotions": 284.99,
                "tyPlusCouponApplicablePrice": 284.99
              },
              "rushDeliveryDuration": 0,
              "lowestPriceDuration": {
                "duration": 0
              },
              "itemNumber": 1254470425,
              "quantity": 490,
              "sellable": true,
              "isWinner": true,
              "freeCargo": false,
              "hasCollectable": false
            }
          ],
          "stamps": [],
          "customValues": [
            {
              "key": "deliveryCountries",
              "value": "AZ"
            }
          ],
          "merchant": {
            "id": 1193645
          },
          "isWinner": true,
          "freeCargo": false
        }
      ],
      "recommendedRetailPrice": null,
      "isRunningOut": false,
      "url": "/genel-markalar/kadin-dikissiz-bilegi-saran-ozel-bant-ic-yuzeyi-peluslu-buyuk-beden-termal-tayt-p-887042058",
      "rating": {
        "averageRating": 4.2272727272727275,
        "totalComments": 22
      },
      "ratingScore": {
        "averageRating": 4.2272727272727275,
        "totalCount": 22
      },
      "hasReviewPhoto": true,
      "stamps": [],
      "tagDetails": [
        {
          "tag": "turuncu_kampanya_urunu",
          "displayName": "Çok Avantajlı Ürün",
          "tagId": 4898,
          "searchable": true,
          "priceTagStamp": true,
          "hasStamp": true
        },
        {
          "tag": "eventdeal",
          "displayName": "",
          "tagId": 1,
          "searchable": false,
          "priceTagStamp": true,
          "hasStamp": false
        }
      ],
      "promotions": [
        {
          "id": 25475568,
          "name": "300 TL ve Üzeri Kargo Bedava (Satıcı Karşılar)",
          "discountType": 7,
          "shortName": "Kargo Bedava",
          "promotionDiscountType": "Cargo",
          "isTyPlus": false
        }
      ],
      "pricePromotion": null,
      "socialProofs": [
        {
          "type": "basketCount",
          "value": "117",
          "translateKey": "socialProof_basketCount",
          "icon": "https://cdn.dsmcdn.com/mobile/search-result/Socialproof_basketcount.png"
        },
        {
          "type": "orderCountL3D",
          "value": "8",
          "translateKey": "socialProof_orderCountL365D",
          "icon": "https://cdn.dsmcdn.com/web/production/rocket-icon.png"
        },
        {
          "type": "favoriteCount",
          "value": "492",
          "translateKey": "socialProof_favoriteCount",
          "icon": "https://cdn.dsmcdn.com/web/production/orange-heart.png"
        }
      ],
      "lowestPriceDuration": 0,
      "stripBadge": {
        "label": "popular",
        "backgroundColor": "#BB0000",
        "textColor": "#FFFFFF"
      },
      "winnerVariant": {
        "unitInfo": {
          "unitPrice": null,
          "typeName": null,
          "unit": null
        },
        "userSegment": null,
        "discountedPriceInfo": "",
        "listingId": "55212ebb9b2725ce484fcbc46115ae1d",
        "barcode": "TYBXL9AXT7SEK25071",
        "groupTagIds": [],
        "variantAttributes": [
          {
            "attributeName": "Beden",
            "attributeValue": "2XL"
          }
        ],
        "tagDetails": [
          {
            "tag": "turuncu_kampanya_urunu",
            "displayName": "Çok Avantajlı Ürün",
            "tagId": 4898,
            "searchable": true,
            "priceTagStamp": true,
            "hasStamp": true
          },
          {
            "tag": "eventdeal",
            "displayName": "",
            "tagId": 1,
            "searchable": false,
            "priceTagStamp": true,
            "hasStamp": false
          }
        ],
        "price": {
          "currency": "TRY",
          "buyingPrice": 0,
          "sellingPrice": 284.99,
          "originalPrice": 284.99,
          "discountedPrice": 284.99,
          "profitMargin": 0,
          "rrp": 0,
          "couponApplicablePrice": 284.99,
          "discountedPriceAfterNoLimitPromotions": 284.99,
          "tyPlusCouponApplicablePrice": 284.99
        },
        "rushDeliveryDuration": 0,
        "lowestPriceDuration": {
          "duration": 0
        },
        "itemNumber": 1254470425,
        "quantity": 490,
        "sellable": true,
        "isWinner": true,
        "freeCargo": false,
        "hasCollectable": false
      },
      "priceChange": "NONE",
      "promotion": [
        {
          "id": 25475568,
          "name": "300 TL ve Üzeri Kargo Bedava (Satıcı Karşılar)",
          "discountType": 7,
          "shortName": "Kargo Bedava",
          "promotionDiscountType": "Cargo",
          "isTyPlus": false
        }
      ],
      "isFlash": false,
      "quantityStatusBadge": {
        "quantity": null,
        "badgeType": null
      }
    },
    {
      "id": 834018779,
      "name": "Lady Büyük Beden Fitness Tayt Crop Sporcu Takımı",
      "inStock": true,
      "brand": {
        "id": 995317,
        "name": "NightLove"
      },
      "webBrand": {
        "id": 995317,
        "name": "NightLove"
      },
      "category": {
        "id": 0,
        "name": ""
      },
      "price": {
        "originalPrice": 599,
        "discountedPrice": 599,
        "oldPrice": 0,
        "sellingPrice": 599,
        "buyingPrice": 599,
        "rrp": 599,
        "pureRrp": 599,
        "favoritedPrice": 0,
        "currency": "TL",
        "originalPriceText": "599,00",
        "discountedPriceText": "599,00",
        "oldPriceText": "0,00",
        "sellingPriceText": "599,00",
        "buyingPriceText": "599,00",
        "rrpText": "599,00"
      },
      "images": [
        "https://cdn.dsmcdn.com/ty1345/product/media/images/prod/QC/20240603/16/46a6862c-6ab4-3eb0-9552-77bdab32795e/1_org_zoom.jpg"
      ],
      "imageUrl": "https://cdn.dsmcdn.com/ty1345/product/media/images/prod/QC/20240603/16/46a6862c-6ab4-3eb0-9552-77bdab32795e/1_org_zoom.jpg",
      "merchantListings": [
        {
          "promotions": [
            {
              "name": "5 Al 4 Öde",
              "promotionDiscountType": "TwoForOne",
              "shortName": "5 Al 4 Öde",
              "id": 25816714,
              "discountType": 2,
              "isApplied": false,
              "isTyPlus": false
            },
            {
              "name": "300 TL ve Üzeri Kargo Bedava (Satıcı Karşılar)",
              "promotionDiscountType": "Cargo",
              "shortName": "Kargo Bedava",
              "id": 23727722,
              "discountType": 7,
              "isApplied": true,
              "isTyPlus": false
            }
          ],
          "variants": [
            {
              "unitInfo": {
                "unitPrice": null,
                "typeName": null,
                "unit": null
              },
              "userSegment": null,
              "discountedPriceInfo": "",
              "listingId": "461aff9262e1e5a8953a7a97600ddcee",
              "barcode": "651231265210",
              "groupTagIds": [],
              "variantAttributes": [
                {
                  "attributeName": "Beden",
                  "attributeValue": "2XL"
                }
              ],
              "tagDetails": [],
              "price": {
                "currency": "TRY",
                "buyingPrice": 0,
                "sellingPrice": 599,
                "originalPrice": 599,
                "discountedPrice": 599,
                "profitMargin": 0,
                "rrp": 0,
                "couponApplicablePrice": 599,
                "discountedPriceAfterNoLimitPromotions": 599,
                "tyPlusCouponApplicablePrice": 599
              },
              "rushDeliveryDuration": 0,
              "lowestPriceDuration": {
                "duration": 0
              },
              "itemNumber": 1119041843,
              "quantity": 91,
              "sellable": true,
              "isWinner": true,
              "freeCargo": true,
              "hasCollectable": false
            }
          ],
          "stamps": [],
          "customValues": [
            {
              "key": "deliveryCountries",
              "value": "AZ"
            },
            {
              "key": "origin",
              "value": "TR"
            }
          ],
          "merchant": {
            "id": 348264
          },
          "isWinner": true,
          "freeCargo": false
        }
      ],
      "recommendedRetailPrice": null,
      "isRunningOut": false,
      "url": "/nightlove/lady-buyuk-beden-fitness-tayt-crop-sporcu-takimi-p-834018779",
      "rating": {
        "averageRating": 3.5,
        "totalComments": 4
      },
      "ratingScore": {
        "averageRating": 3.5,
        "totalCount": 4
      },
      "hasReviewPhoto": true,
      "stamps": [],
      "tagDetails": [],
      "promotions": [
        {
          "id": 25816714,
          "name": "5 Al 4 Öde",
          "discountType": 2,
          "shortName": "5 Al 4 Öde",
          "promotionDiscountType": "TwoForOne",
          "isTyPlus": false
        },
        {
          "id": 23727722,
          "name": "300 TL ve Üzeri Kargo Bedava (Satıcı Karşılar)",
          "discountType": 7,
          "shortName": "Kargo Bedava",
          "promotionDiscountType": "Cargo",
          "isTyPlus": false
        }
      ],
      "pricePromotion": null,
      "socialProofs": [
        {
          "type": "basketCount",
          "value": "6",
          "translateKey": "socialProof_basketCount",
          "icon": "https://cdn.dsmcdn.com/mobile/search-result/Socialproof_basketcount.png"
        },
        {
          "type": "orderCountL3D",
          "value": "2",
          "translateKey": "socialProof_orderCountL365D",
          "icon": "https://cdn.dsmcdn.com/web/production/rocket-icon.png"
        },
        {
          "type": "favoriteCount",
          "value": "226",
          "translateKey": "socialProof_favoriteCount",
          "icon": "https://cdn.dsmcdn.com/web/production/orange-heart.png"
        }
      ],
      "lowestPriceDuration": 0,
      "stripBadge": {
        "label": "rank_increased",
        "value": 1,
        "icon": "https://cdn.dsmcdn.com/sfint/prod/fp/up-list_1760345139449.png",
        "backgroundColor": "#0BC15C",
        "textColor": "#FFFFFF"
      },
      "winnerVariant": {
        "unitInfo": {
          "unitPrice": null,
          "typeName": null,
          "unit": null
        },
        "userSegment": null,
        "discountedPriceInfo": "",
        "listingId": "461aff9262e1e5a8953a7a97600ddcee",
        "barcode": "651231265210",
        "groupTagIds": [],
        "variantAttributes": [
          {
            "attributeName": "Beden",
            "attributeValue": "2XL"
          }
        ],
        "tagDetails": [],
        "price": {
          "currency": "TRY",
          "buyingPrice": 0,
          "sellingPrice": 599,
          "originalPrice": 599,
          "discountedPrice": 599,
          "profitMargin": 0,
          "rrp": 0,
          "couponApplicablePrice": 599,
          "discountedPriceAfterNoLimitPromotions": 599,
          "tyPlusCouponApplicablePrice": 599
        },
        "rushDeliveryDuration": 0,
        "lowestPriceDuration": {
          "duration": 0
        },
        "itemNumber": 1119041843,
        "quantity": 91,
        "sellable": true,
        "isWinner": true,
        "freeCargo": true,
        "hasCollectable": false
      },
      "priceChange": "NONE",
      "promotion": [
        {
          "id": 25816714,
          "name": "5 Al 4 Öde",
          "discountType": 2,
          "shortName": "5 Al 4 Öde",
          "promotionDiscountType": "TwoForOne",
          "isTyPlus": false
        }
      ],
      "isFlash": false,
      "quantityStatusBadge": {
        "quantity": null,
        "badgeType": null
      }
    },
    {
      "id": 1065945217,
      "name": "Büyük beden Peluş Tayt İçi Peluş Termal İçlik",
      "inStock": true,
      "brand": {
        "id": 1809576,
        "name": "ICOLEXİN"
      },
      "webBrand": {
        "id": 1809576,
        "name": "ICOLEXİN"
      },
      "category": {
        "id": 0,
        "name": ""
      },
      "price": {
        "originalPrice": 599,
        "discountedPrice": 599,
        "oldPrice": 0,
        "sellingPrice": 599,
        "buyingPrice": 599,
        "rrp": 599,
        "pureRrp": 599,
        "favoritedPrice": 0,
        "currency": "TL",
        "originalPriceText": "599,00",
        "discountedPriceText": "599,00",
        "oldPriceText": "0,00",
        "sellingPriceText": "599,00",
        "buyingPriceText": "599,00",
        "rrpText": "599,00"
      },
      "images": [
        "https://cdn.dsmcdn.com/ty1798/prod/QC_PREP/20251212/19/6fd9d591-52ea-3ebf-bc95-bbd574807445/1_org_zoom.jpg",
        "https://cdn.dsmcdn.com/ty1797/prod/QC_PREP/20251212/19/7f5214e6-0f8a-321a-80e4-9dea884082ba/1_org_zoom.jpg",
        "https://cdn.dsmcdn.com/ty1799/prod/QC_PREP/20251212/19/50ceb103-82a1-35be-aa17-1fac27c692f7/1_org_zoom.jpg",
        "https://cdn.dsmcdn.com/ty1799/prod/QC_PREP/20251212/19/14318168-0f75-3e86-a974-c48772f80332/1_org_zoom.jpg",
        "https://cdn.dsmcdn.com/ty1797/prod/QC_PREP/20251212/19/13646923-f503-3000-80c7-1ff33664766d/1_org_zoom.jpg",
        "https://cdn.dsmcdn.com/ty1797/prod/QC_PREP/20251212/19/bfd1788d-8f31-3e3d-9b4e-765d24409293/1_org_zoom.jpg",
        "https://cdn.dsmcdn.com/ty1798/prod/QC_PREP/20251212/19/496cc971-141c-3f19-b244-49af38c710a4/1_org_zoom.jpg"
      ],
      "imageUrl": "https://cdn.dsmcdn.com/ty1798/prod/QC_PREP/20251212/19/6fd9d591-52ea-3ebf-bc95-bbd574807445/1_org_zoom.jpg",
      "merchantListings": [
        {
          "promotions": [
            {
              "name": "300 TL ve Üzeri Kargo Bedava (Satıcı Karşılar)",
              "promotionDiscountType": "Cargo",
              "shortName": "Kargo Bedava",
              "id": 23785046,
              "discountType": 7,
              "isApplied": true,
              "isTyPlus": false
            }
          ],
          "variants": [
            {
              "unitInfo": {
                "unitPrice": null,
                "typeName": null,
                "unit": null
              },
              "userSegment": null,
              "discountedPriceInfo": "",
              "listingId": "fe920eaa2496598348e15d71099830fa",
              "barcode": "IC25000-SM",
              "groupTagIds": [],
              "variantAttributes": [
                {
                  "attributeName": "Beden",
                  "attributeValue": "S/M"
                }
              ],
              "tagDetails": [],
              "price": {
                "currency": "TRY",
                "buyingPrice": 0,
                "sellingPrice": 599,
                "originalPrice": 599,
                "discountedPrice": 599,
                "profitMargin": 0,
                "rrp": 0,
                "couponApplicablePrice": 599,
                "discountedPriceAfterNoLimitPromotions": 599,
                "tyPlusCouponApplicablePrice": 599
              },
              "rushDeliveryDuration": 24,
              "lowestPriceDuration": {
                "duration": 0
              },
              "itemNumber": 1473904288,
              "quantity": 1000,
              "sellable": true,
              "isWinner": true,
              "freeCargo": true,
              "hasCollectable": false
            }
          ],
          "stamps": [],
          "customValues": [
            {
              "key": "deliveryCountries",
              "value": "AZ"
            }
          ],
          "merchant": {
            "id": 773640
          },
          "isWinner": true,
          "freeCargo": false
        }
      ],
      "recommendedRetailPrice": null,
      "isRunningOut": false,
      "url": "/icolexin/buyuk-beden-pelus-tayt-ici-pelus-termal-iclik-p-1065945217",
      "rating": {
        "averageRating": 0,
        "totalComments": 0
      },
      "ratingScore": {
        "averageRating": 0,
        "totalCount": 0
      },
      "hasReviewPhoto": false,
      "stamps": [],
      "tagDetails": [],
      "promotions": [
        {
          "id": 23785046,
          "name": "300 TL ve Üzeri Kargo Bedava (Satıcı Karşılar)",
          "discountType": 7,
          "shortName": "Kargo Bedava",
          "promotionDiscountType": "Cargo",
          "isTyPlus": false
        }
      ],
      "pricePromotion": null,
      "socialProofs": [
        {
          "type": "basketCount",
          "value": "13",
          "translateKey": "socialProof_basketCount",
          "icon": "https://cdn.dsmcdn.com/mobile/search-result/Socialproof_basketcount.png"
        },
        {
          "type": "orderCountL3D",
          "value": "2",
          "translateKey": "socialProof_orderCountL365D",
          "icon": "https://cdn.dsmcdn.com/web/production/rocket-icon.png"
        },
        {
          "type": "favoriteCount",
          "value": "10",
          "translateKey": "socialProof_favoriteCount",
          "icon": "https://cdn.dsmcdn.com/web/production/orange-heart.png"
        }
      ],
      "lowestPriceDuration": 0,
      "winnerVariant": {
        "unitInfo": {
          "unitPrice": null,
          "typeName": null,
          "unit": null
        },
        "userSegment": null,
        "discountedPriceInfo": "",
        "listingId": "fe920eaa2496598348e15d71099830fa",
        "barcode": "IC25000-SM",
        "groupTagIds": [],
        "variantAttributes": [
          {
            "attributeName": "Beden",
            "attributeValue": "S/M"
          }
        ],
        "tagDetails": [],
        "price": {
          "currency": "TRY",
          "buyingPrice": 0,
          "sellingPrice": 599,
          "originalPrice": 599,
          "discountedPrice": 599,
          "profitMargin": 0,
          "rrp": 0,
          "couponApplicablePrice": 599,
          "discountedPriceAfterNoLimitPromotions": 599,
          "tyPlusCouponApplicablePrice": 599
        },
        "rushDeliveryDuration": 24,
        "lowestPriceDuration": {
          "duration": 0
        },
        "itemNumber": 1473904288,
        "quantity": 1000,
        "sellable": true,
        "isWinner": true,
        "freeCargo": true,
        "hasCollectable": false
      },
      "priceChange": "NONE",
      "promotion": [
        {
          "id": 23785046,
          "name": "300 TL ve Üzeri Kargo Bedava (Satıcı Karşılar)",
          "discountType": 7,
          "shortName": "Kargo Bedava",
          "promotionDiscountType": "Cargo",
          "isTyPlus": false
        }
      ],
      "isFlash": false,
      "quantityStatusBadge": {
        "quantity": null,
        "badgeType": null
      }
    },
    {
      "id": 960268690,
      "name": "| Battal Beden Kışlık Termal 3 Renk 3 Adet Spor Tayt",
      "inStock": true,
      "brand": {
        "id": 1068421,
        "name": "Isıl Termal"
      },
      "webBrand": {
        "id": 1068421,
        "name": "Isıl Termal"
      },
      "category": {
        "id": 0,
        "name": ""
      },
      "price": {
        "originalPrice": 489,
        "discountedPrice": 489,
        "oldPrice": 0,
        "sellingPrice": 489,
        "buyingPrice": 489,
        "rrp": 489,
        "pureRrp": 489,
        "favoritedPrice": 0,
        "currency": "TL",
        "originalPriceText": "489,00",
        "discountedPriceText": "489,00",
        "oldPriceText": "0,00",
        "sellingPriceText": "489,00",
        "buyingPriceText": "489,00",
        "rrpText": "489,00"
      },
      "images": [
        "https://cdn.dsmcdn.com/ty1714/prod/QC_PREP/20250724/12/02bd523b-93e0-356e-b591-d0b065c6ded6/1_org_zoom.jpg",
        "https://cdn.dsmcdn.com/ty1714/prod/QC_PREP/20250724/12/0648e20f-ea8a-3443-906b-e144be8bfe92/1_org_zoom.jpg",
        "https://cdn.dsmcdn.com/ty1713/prod/QC_PREP/20250724/12/480c60c4-aa6d-3892-bd30-90c91345ce43/1_org_zoom.jpg",
        "https://cdn.dsmcdn.com/ty1715/prod/QC_PREP/20250724/12/aa55c04f-5a84-3538-b18e-9afb15429b5f/1_org_zoom.jpg",
        "https://cdn.dsmcdn.com/ty1714/prod/QC_PREP/20250724/12/66874962-8194-3983-9a66-998accbef9fc/1_org_zoom.jpg",
        "https://cdn.dsmcdn.com/ty1713/prod/QC_PREP/20250724/12/4bc52674-e43d-3016-85df-fe14baacdcce/1_org_zoom.jpg",
        "https://cdn.dsmcdn.com/ty1715/prod/QC_PREP/20250724/12/3fc11e9a-1286-390e-a39b-aad89f268525/1_org_zoom.jpg",
        "https://cdn.dsmcdn.com/ty1714/prod/QC_PREP/20250724/12/c87b73f6-658b-3c20-85d4-b0fcf3beaadb/1_org_zoom.jpg"
      ],
      "imageUrl": "https://cdn.dsmcdn.com/ty1714/prod/QC_PREP/20250724/12/02bd523b-93e0-356e-b591-d0b065c6ded6/1_org_zoom.jpg",
      "merchantListings": [
        {
          "promotions": [
            {
              "name": "Trendyol Plus'a Özel Fiyat",
              "promotionDiscountType": "DiscountOnBasket",
              "shortName": "Plus'a Özel Fiyat",
              "id": 25643430,
              "discountType": 2,
              "isApplied": true,
              "isTyPlus": true
            },
            {
              "name": "300 TL ve Üzeri Kargo Bedava (Satıcı Karşılar)",
              "promotionDiscountType": "Cargo",
              "shortName": "Kargo Bedava",
              "id": 23735938,
              "discountType": 7,
              "isApplied": true,
              "isTyPlus": false
            }
          ],
          "variants": [
            {
              "unitInfo": {
                "unitPrice": null,
                "typeName": null,
                "unit": null
              },
              "userSegment": null,
              "discountedPriceInfo": "",
              "listingId": "8ad59e8f4a608155f3419c86cb0a6d1e",
              "barcode": "56546544165465465",
              "groupTagIds": [
                "0e2a31ba-83ec-401f-bd51-7b8a2f2a656a"
              ],
              "variantAttributes": [
                {
                  "attributeName": "Beden",
                  "attributeValue": "Battal Boy"
                }
              ],
              "tagDetails": [],
              "price": {
                "currency": "TRY",
                "buyingPrice": 0,
                "sellingPrice": 489,
                "originalPrice": 489,
                "discountedPrice": 489,
                "profitMargin": 0,
                "rrp": 0,
                "couponApplicablePrice": 489,
                "discountedPriceAfterNoLimitPromotions": 489,
                "tyPlusCouponApplicablePrice": 440.1
              },
              "rushDeliveryDuration": 24,
              "lowestPriceDuration": {
                "duration": 0
              },
              "itemNumber": 1359018898,
              "quantity": 4789,
              "sellable": true,
              "isWinner": true,
              "freeCargo": true,
              "hasCollectable": true
            }
          ],
          "stamps": [],
          "customValues": [
            {
              "key": "deliveryCountries",
              "value": "AZ"
            }
          ],
          "merchant": {
            "id": 306880
          },
          "isWinner": true,
          "freeCargo": false
        }
      ],
      "recommendedRetailPrice": null,
      "isRunningOut": false,
      "url": "/isil-termal/battal-beden-kislik-termal-3-renk-3-adet-spor-tayt-p-960268690",
      "rating": {
        "averageRating": 4.2,
        "totalComments": 25
      },
      "ratingScore": {
        "averageRating": 4.2,
        "totalCount": 25
      },
      "hasReviewPhoto": true,
      "stamps": [],
      "tagDetails": [],
      "promotions": [
        {
          "id": 25643430,
          "name": "Trendyol Plus'a Özel Fiyat",
          "discountType": 2,
          "shortName": "Plus'a Özel Fiyat",
          "promotionDiscountType": "DiscountOnBasket",
          "isTyPlus": true
        },
        {
          "id": 23735938,
          "name": "300 TL ve Üzeri Kargo Bedava (Satıcı Karşılar)",
          "discountType": 7,
          "shortName": "Kargo Bedava",
          "promotionDiscountType": "Cargo",
          "isTyPlus": false
        }
      ],
      "pricePromotion": {
        "value": 440.1,
        "text": "440,10",
        "type": "ty_plus_price",
        "oldPrice": 489,
        "oldPriceText": "489,00"
      },
      "socialProofs": [
        {
          "type": "basketCount",
          "value": "98",
          "translateKey": "socialProof_basketCount",
          "icon": "https://cdn.dsmcdn.com/mobile/search-result/Socialproof_basketcount.png"
        },
        {
          "type": "orderCountL3D",
          "value": "2",
          "translateKey": "socialProof_orderCountL365D",
          "icon": "https://cdn.dsmcdn.com/web/production/rocket-icon.png"
        },
        {
          "type": "favoriteCount",
          "value": "571",
          "translateKey": "socialProof_favoriteCount",
          "icon": "https://cdn.dsmcdn.com/web/production/orange-heart.png"
        }
      ],
      "lowestPriceDuration": 0,
      "stripBadge": {
        "label": "popular",
        "backgroundColor": "#BB0000",
        "textColor": "#FFFFFF"
      },
      "winnerVariant": {
        "unitInfo": {
          "unitPrice": null,
          "typeName": null,
          "unit": null
        },
        "userSegment": null,
        "discountedPriceInfo": "",
        "listingId": "8ad59e8f4a608155f3419c86cb0a6d1e",
        "barcode": "56546544165465465",
        "groupTagIds": [
          "0e2a31ba-83ec-401f-bd51-7b8a2f2a656a"
        ],
        "variantAttributes": [
          {
            "attributeName": "Beden",
            "attributeValue": "Battal Boy"
          }
        ],
        "tagDetails": [],
        "price": {
          "currency": "TRY",
          "buyingPrice": 0,
          "sellingPrice": 489,
          "originalPrice": 489,
          "discountedPrice": 489,
          "profitMargin": 0,
          "rrp": 0,
          "couponApplicablePrice": 489,
          "discountedPriceAfterNoLimitPromotions": 489,
          "tyPlusCouponApplicablePrice": 440.1
        },
        "rushDeliveryDuration": 24,
        "lowestPriceDuration": {
          "duration": 0
        },
        "itemNumber": 1359018898,
        "quantity": 4789,
        "sellable": true,
        "isWinner": true,
        "freeCargo": true,
        "hasCollectable": true
      },
      "priceChange": "NONE",
      "promotion": [
        {
          "id": 25643430,
          "name": "Trendyol Plus'a Özel Fiyat",
          "discountType": 2,
          "shortName": "Plus'a Özel Fiyat",
          "promotionDiscountType": "DiscountOnBasket",
          "isTyPlus": true
        }
      ],
      "isFlash": false,
      "quantityStatusBadge": {
        "quantity": null,
        "badgeType": null
      }
    },
    {
      "id": 1018204842,
      "name": "SLİMX 2 BEDEN SIKILAŞTIRICI YÜKSEK BEL İSPANYOL PAÇA TOPARLAYICI BÜYÜK BEDEN SPOR TAYT",
      "inStock": true,
      "brand": {
        "id": 1806645,
        "name": "Fitsauna"
      },
      "webBrand": {
        "id": 1806645,
        "name": "Fitsauna"
      },
      "category": {
        "id": 0,
        "name": ""
      },
      "price": {
        "originalPrice": 799.99,
        "discountedPrice": 799.99,
        "oldPrice": 0,
        "sellingPrice": 799.99,
        "buyingPrice": 799.99,
        "rrp": 799.99,
        "pureRrp": 799.99,
        "favoritedPrice": 0,
        "currency": "TL",
        "originalPriceText": "799,99",
        "discountedPriceText": "799,99",
        "oldPriceText": "0,00",
        "sellingPriceText": "799,99",
        "buyingPriceText": "799,99",
        "rrpText": "799,99"
      },
      "images": [
        "https://cdn.dsmcdn.com/ty1767/prod/QC_PREP/20251008/18/a6a5974e-9fc4-39b4-aca3-4952081db463/1_org_zoom.jpg",
        "https://cdn.dsmcdn.com/ty1769/prod/QC_PREP/20251008/18/ddaa26a1-da85-3a44-905e-03cde42e68ad/1_org_zoom.jpg",
        "https://cdn.dsmcdn.com/ty1768/prod/QC_PREP/20251008/18/7b428609-d807-34a8-b5f5-5b62036c7fba/1_org_zoom.jpg",
        "https://cdn.dsmcdn.com/ty1767/prod/QC_PREP/20251008/18/6230b0db-181e-3bc9-ad70-e771317ee189/1_org_zoom.jpg",
        "https://cdn.dsmcdn.com/ty1768/prod/QC_PREP/20251008/18/b7819902-a543-354d-b4a1-625e0193d094/1_org_zoom.jpg",
        "https://cdn.dsmcdn.com/ty1769/prod/QC_PREP/20251008/18/1b95afe9-1cca-3da5-87b5-c0a84663e6bb/1_org_zoom.jpg"
      ],
      "imageUrl": "https://cdn.dsmcdn.com/ty1767/prod/QC_PREP/20251008/18/a6a5974e-9fc4-39b4-aca3-4952081db463/1_org_zoom.jpg",
      "merchantListings": [
        {
          "promotions": [
            {
              "name": "300 TL ve Üzeri Kargo Bedava (Satıcı Karşılar)",
              "promotionDiscountType": "Cargo",
              "shortName": "Kargo Bedava",
              "id": 23704629,
              "discountType": 7,
              "isApplied": true,
              "isTyPlus": false
            }
          ],
          "variants": [
            {
              "unitInfo": {
                "unitPrice": null,
                "typeName": null,
                "unit": null
              },
              "userSegment": null,
              "discountedPriceInfo": "",
              "listingId": "dbf0d0ea298fd94e22fe47930544f76b",
              "barcode": "FS-4030-S",
              "groupTagIds": [],
              "variantAttributes": [
                {
                  "attributeName": "Beden",
                  "attributeValue": "S"
                }
              ],
              "tagDetails": [],
              "price": {
                "currency": "TRY",
                "buyingPrice": 0,
                "sellingPrice": 799.99,
                "originalPrice": 799.99,
                "discountedPrice": 799.99,
                "profitMargin": 0,
                "rrp": 0,
                "couponApplicablePrice": 799.99,
                "discountedPriceAfterNoLimitPromotions": 799.99,
                "tyPlusCouponApplicablePrice": 498.76
              },
              "rushDeliveryDuration": 24,
              "lowestPriceDuration": {
                "duration": 0
              },
              "itemNumber": 1414454700,
              "quantity": 96,
              "sellable": true,
              "isWinner": true,
              "freeCargo": true,
              "hasCollectable": false
            }
          ],
          "stamps": [],
          "customValues": [
            {
              "key": "deliveryCountries",
              "value": "AZ"
            }
          ],
          "merchant": {
            "id": 765355
          },
          "isWinner": true,
          "freeCargo": true
        }
      ],
      "recommendedRetailPrice": null,
      "isRunningOut": false,
      "url": "/fitsauna/slimx-2-beden-sikilastirici-yuksek-bel-ispanyol-paca-toparlayici-buyuk-beden-spor-tayt-p-1018204842",
      "rating": {
        "averageRating": 3,
        "totalComments": 2
      },
      "ratingScore": {
        "averageRating": 3,
        "totalCount": 2
      },
      "hasReviewPhoto": false,
      "stamps": [],
      "tagDetails": [],
      "promotions": [
        {
          "id": 23704629,
          "name": "300 TL ve Üzeri Kargo Bedava (Satıcı Karşılar)",
          "discountType": 7,
          "shortName": "Kargo Bedava",
          "promotionDiscountType": "Cargo",
          "isTyPlus": false
        }
      ],
      "pricePromotion": {
        "value": 498.76,
        "text": "498,76",
        "type": "ty_plus_price",
        "oldPrice": 799.99,
        "oldPriceText": "799,99"
      },
      "socialProofs": [
        {
          "type": "basketCount",
          "value": "7",
          "translateKey": "socialProof_basketCount",
          "icon": "https://cdn.dsmcdn.com/mobile/search-result/Socialproof_basketcount.png"
        },
        {
          "type": "orderCountL3D",
          "value": "1",
          "translateKey": "socialProof_orderCountL365D",
          "icon": "https://cdn.dsmcdn.com/web/production/rocket-icon.png"
        },
        {
          "type": "favoriteCount",
          "value": "18",
          "translateKey": "socialProof_favoriteCount",
          "icon": "https://cdn.dsmcdn.com/web/production/orange-heart.png"
        }
      ],
      "lowestPriceDuration": 0,
      "stripBadge": {
        "label": "rank_increased",
        "value": 3,
        "icon": "https://cdn.dsmcdn.com/sfint/prod/fp/up-list_1760345139449.png",
        "backgroundColor": "#0BC15C",
        "textColor": "#FFFFFF"
      },
      "winnerVariant": {
        "unitInfo": {
          "unitPrice": null,
          "typeName": null,
          "unit": null
        },
        "userSegment": null,
        "discountedPriceInfo": "",
        "listingId": "dbf0d0ea298fd94e22fe47930544f76b",
        "barcode": "FS-4030-S",
        "groupTagIds": [],
        "variantAttributes": [
          {
            "attributeName": "Beden",
            "attributeValue": "S"
          }
        ],
        "tagDetails": [],
        "price": {
          "currency": "TRY",
          "buyingPrice": 0,
          "sellingPrice": 799.99,
          "originalPrice": 799.99,
          "discountedPrice": 799.99,
          "profitMargin": 0,
          "rrp": 0,
          "couponApplicablePrice": 799.99,
          "discountedPriceAfterNoLimitPromotions": 799.99,
          "tyPlusCouponApplicablePrice": 498.76
        },
        "rushDeliveryDuration": 24,
        "lowestPriceDuration": {
          "duration": 0
        },
        "itemNumber": 1414454700,
        "quantity": 96,
        "sellable": true,
        "isWinner": true,
        "freeCargo": true,
        "hasCollectable": false
      },
      "priceChange": "NONE",
      "promotion": [
        {
          "id": 23704629,
          "name": "300 TL ve Üzeri Kargo Bedava (Satıcı Karşılar)",
          "discountType": 7,
          "shortName": "Kargo Bedava",
          "promotionDiscountType": "Cargo",
          "isTyPlus": false
        }
      ],
      "isFlash": false,
      "quantityStatusBadge": {
        "quantity": null,
        "badgeType": null
      }
    },
    {
      "id": 672586375,
      "name": "Kadın Çelik Örme Büyük Beden Toparlayıcı Sıkılaştırcı Yüksek Bel Siyah Tayt",
      "inStock": true,
      "brand": {
        "id": 1032099,
        "name": "mirox"
      },
      "webBrand": {
        "id": 1032099,
        "name": "mirox"
      },
      "category": {
        "id": 0,
        "name": ""
      },
      "price": {
        "originalPrice": 289,
        "discountedPrice": 289,
        "oldPrice": 0,
        "sellingPrice": 289,
        "buyingPrice": 289,
        "rrp": 289,
        "pureRrp": 289,
        "favoritedPrice": 0,
        "currency": "TL",
        "originalPriceText": "289,00",
        "discountedPriceText": "289,00",
        "oldPriceText": "0,00",
        "sellingPriceText": "289,00",
        "buyingPriceText": "289,00",
        "rrpText": "289,00"
      },
      "images": [
        "https://cdn.dsmcdn.com/ty1539/product/media/images/ty1541/prod/QC/20240913/10/941a6cc9-bbdc-3c80-bb0c-a02c12c4236f/1_org_zoom.jpg",
        "https://cdn.dsmcdn.com/ty1541/product/media/images/ty1539/prod/QC/20240913/10/cce9ad6a-ef88-30e2-a362-c32d9be8f440/1_org_zoom.jpg",
        "https://cdn.dsmcdn.com/ty1539/product/media/images/ty1540/prod/QC/20240913/10/7770a21a-e328-3807-ac53-721b84b651d4/1_org_zoom.jpg"
      ],
      "imageUrl": "https://cdn.dsmcdn.com/ty1539/product/media/images/ty1541/prod/QC/20240913/10/941a6cc9-bbdc-3c80-bb0c-a02c12c4236f/1_org_zoom.jpg",
      "merchantListings": [
        {
          "promotions": [
            {
              "name": "850 TL'ye 10 TL İndirim",
              "promotionDiscountType": "DiscountOnBasket",
              "shortName": "Çok Al Az Öde",
              "id": 25888625,
              "discountType": 2,
              "isApplied": false,
              "isTyPlus": false
            },
            {
              "name": "5 Adet ve Üzeri %1 İndirim",
              "promotionDiscountType": "TwoForOne",
              "shortName": "5 Adede %1",
              "id": 25888633,
              "discountType": 2,
              "isApplied": false,
              "isTyPlus": false
            },
            {
              "name": "300 TL ve Üzeri Kargo Bedava (Satıcı Karşılar)",
              "promotionDiscountType": "Cargo",
              "shortName": "Kargo Bedava",
              "id": 23773728,
              "discountType": 7,
              "isApplied": false,
              "isTyPlus": false
            }
          ],
          "variants": [
            {
              "unitInfo": {
                "unitPrice": null,
                "typeName": null,
                "unit": null
              },
              "userSegment": null,
              "discountedPriceInfo": "",
              "listingId": "c667f64dbea5ac900ee57c37868053c3",
              "barcode": "1708017283058",
              "groupTagIds": [],
              "variantAttributes": [
                {
                  "attributeName": "Beden",
                  "attributeValue": "2XL"
                }
              ],
              "tagDetails": [
                {
                  "tag": "beyaz_kampanya_urunu",
                  "displayName": "Beyaz Kampanya Ürünü",
                  "tagId": 1,
                  "searchable": false,
                  "priceTagStamp": true,
                  "hasStamp": false
                }
              ],
              "price": {
                "currency": "TRY",
                "buyingPrice": 0,
                "sellingPrice": 289,
                "originalPrice": 289,
                "discountedPrice": 289,
                "profitMargin": 0,
                "rrp": 0,
                "couponApplicablePrice": 289,
                "discountedPriceAfterNoLimitPromotions": 289,
                "tyPlusCouponApplicablePrice": 289
              },
              "rushDeliveryDuration": 24,
              "lowestPriceDuration": {
                "duration": 0
              },
              "itemNumber": 889885927,
              "quantity": 18,
              "sellable": true,
              "isWinner": true,
              "freeCargo": false,
              "hasCollectable": false
            }
          ],
          "stamps": [],
          "customValues": [
            {
              "key": "deliveryCountries",
              "value": "AZ"
            },
            {
              "key": "origin",
              "value": "TR"
            }
          ],
          "merchant": {
            "id": 742480
          },
          "isWinner": true,
          "freeCargo": false
        }
      ],
      "recommendedRetailPrice": null,
      "isRunningOut": false,
      "url": "/mirox/kadin-celik-orme-buyuk-beden-toparlayici-sikilastirci-yuksek-bel-siyah-tayt-p-672586375",
      "rating": {
        "averageRating": 3.4285714285714284,
        "totalComments": 7
      },
      "ratingScore": {
        "averageRating": 3.4285714285714284,
        "totalCount": 7
      },
      "hasReviewPhoto": true,
      "stamps": [],
      "tagDetails": [
        {
          "tag": "beyaz_kampanya_urunu",
          "displayName": "Beyaz Kampanya Ürünü",
          "tagId": 1,
          "searchable": false,
          "priceTagStamp": true,
          "hasStamp": false
        }
      ],
      "promotions": [
        {
          "id": 25888625,
          "name": "850 TL'ye 10 TL İndirim",
          "discountType": 2,
          "shortName": "Çok Al Az Öde",
          "promotionDiscountType": "DiscountOnBasket",
          "isTyPlus": false
        },
        {
          "id": 25888633,
          "name": "5 Adet ve Üzeri %1 İndirim",
          "discountType": 2,
          "shortName": "5 Adede %1",
          "promotionDiscountType": "TwoForOne",
          "isTyPlus": false
        },
        {
          "id": 23773728,
          "name": "300 TL ve Üzeri Kargo Bedava (Satıcı Karşılar)",
          "discountType": 7,
          "shortName": "Kargo Bedava",
          "promotionDiscountType": "Cargo",
          "isTyPlus": false
        }
      ],
      "pricePromotion": null,
      "socialProofs": [
        {
          "type": "basketCount",
          "value": "19",
          "translateKey": "socialProof_basketCount",
          "icon": "https://cdn.dsmcdn.com/mobile/search-result/Socialproof_basketcount.png"
        },
        {
          "type": "orderCountL3D",
          "value": "1",
          "translateKey": "socialProof_orderCountL365D",
          "icon": "https://cdn.dsmcdn.com/web/production/rocket-icon.png"
        },
        {
          "type": "favoriteCount",
          "value": "164",
          "translateKey": "socialProof_favoriteCount",
          "icon": "https://cdn.dsmcdn.com/web/production/orange-heart.png"
        }
      ],
      "lowestPriceDuration": 0,
      "winnerVariant": {
        "unitInfo": {
          "unitPrice": null,
          "typeName": null,
          "unit": null
        },
        "userSegment": null,
        "discountedPriceInfo": "",
        "listingId": "c667f64dbea5ac900ee57c37868053c3",
        "barcode": "1708017283058",
        "groupTagIds": [],
        "variantAttributes": [
          {
            "attributeName": "Beden",
            "attributeValue": "2XL"
          }
        ],
        "tagDetails": [
          {
            "tag": "beyaz_kampanya_urunu",
            "displayName": "Beyaz Kampanya Ürünü",
            "tagId": 1,
            "searchable": false,
            "priceTagStamp": true,
            "hasStamp": false
          }
        ],
        "price": {
          "currency": "TRY",
          "buyingPrice": 0,
          "sellingPrice": 289,
          "originalPrice": 289,
          "discountedPrice": 289,
          "profitMargin": 0,
          "rrp": 0,
          "couponApplicablePrice": 289,
          "discountedPriceAfterNoLimitPromotions": 289,
          "tyPlusCouponApplicablePrice": 289
        },
        "rushDeliveryDuration": 24,
        "lowestPriceDuration": {
          "duration": 0
        },
        "itemNumber": 889885927,
        "quantity": 18,
        "sellable": true,
        "isWinner": true,
        "freeCargo": false,
        "hasCollectable": false
      },
      "priceChange": "NONE",
      "promotion": [
        {
          "id": 25888625,
          "name": "850 TL'ye 10 TL İndirim",
          "discountType": 2,
          "shortName": "Çok Al Az Öde",
          "promotionDiscountType": "DiscountOnBasket",
          "isTyPlus": false
        }
      ],
      "isFlash": false,
      "quantityStatusBadge": {
        "quantity": null,
        "badgeType": "RUNNING_OUT"
      }
    },
    {
      "id": 1072610731,
      "name": "Erkek İçi Peluş Termal Tayt Battal Büyük Beden Kışlık Peluş Tayt İçlik",
      "inStock": true,
      "brand": {
        "id": 1440061,
        "name": "MODASFORM"
      },
      "webBrand": {
        "id": 1440061,
        "name": "MODASFORM"
      },
      "category": {
        "id": 0,
        "name": ""
      },
      "price": {
        "originalPrice": 699,
        "discountedPrice": 699,
        "oldPrice": 0,
        "sellingPrice": 699,
        "buyingPrice": 699,
        "rrp": 699,
        "pureRrp": 699,
        "favoritedPrice": 0,
        "currency": "TL",
        "originalPriceText": "699,00",
        "discountedPriceText": "699,00",
        "oldPriceText": "0,00",
        "sellingPriceText": "699,00",
        "buyingPriceText": "699,00",
        "rrpText": "699,00"
      },
      "images": [
        "https://cdn.dsmcdn.com/ty1800/prod/QC_PREP/20251218/20/e314088c-8e1e-3217-b458-2e554f8e3c4b/1_org_zoom.jpg",
        "https://cdn.dsmcdn.com/ty1801/prod/QC_PREP/20251218/20/b894e46d-53b2-35d8-8f6d-1d0b5564738d/1_org_zoom.jpg",
        "https://cdn.dsmcdn.com/ty1802/prod/QC_PREP/20251218/20/9ead14b3-5f2e-3442-9c45-12086d60cf8e/1_org_zoom.jpg"
      ],
      "imageUrl": "https://cdn.dsmcdn.com/ty1800/prod/QC_PREP/20251218/20/e314088c-8e1e-3217-b458-2e554f8e3c4b/1_org_zoom.jpg",
      "merchantListings": [
        {
          "promotions": [
            {
              "name": "300 TL ve Üzeri Kargo Bedava (Satıcı Karşılar)",
              "promotionDiscountType": "Cargo",
              "shortName": "Kargo Bedava",
              "id": 23749532,
              "discountType": 7,
              "isApplied": true,
              "isTyPlus": false
            }
          ],
          "variants": [
            {
              "unitInfo": {
                "unitPrice": null,
                "typeName": null,
                "unit": null
              },
              "userSegment": null,
              "discountedPriceInfo": "",
              "listingId": "d1a43f72a1a5aba35b6f9d24010b1911",
              "barcode": "Ms-106",
              "groupTagIds": [],
              "variantAttributes": [
                {
                  "attributeName": "Beden",
                  "attributeValue": "S"
                }
              ],
              "tagDetails": [],
              "price": {
                "currency": "TRY",
                "buyingPrice": 0,
                "sellingPrice": 699,
                "originalPrice": 699,
                "discountedPrice": 699,
                "profitMargin": 0,
                "rrp": 0,
                "couponApplicablePrice": 699,
                "discountedPriceAfterNoLimitPromotions": 699,
                "tyPlusCouponApplicablePrice": 699
              },
              "rushDeliveryDuration": 24,
              "lowestPriceDuration": {
                "duration": 0
              },
              "itemNumber": 1482110120,
              "quantity": 1000,
              "sellable": true,
              "isWinner": true,
              "freeCargo": true,
              "hasCollectable": true
            }
          ],
          "stamps": [],
          "customValues": [
            {
              "key": "deliveryCountries",
              "value": "AZ"
            }
          ],
          "merchant": {
            "id": 532317
          },
          "isWinner": true,
          "freeCargo": false
        }
      ],
      "recommendedRetailPrice": null,
      "isRunningOut": false,
      "url": "/modasform/erkek-ici-pelus-termal-tayt-battal-buyuk-beden-kislik-pelus-tayt-iclik-p-1072610731",
      "rating": {
        "averageRating": 5,
        "totalComments": 1
      },
      "ratingScore": {
        "averageRating": 5,
        "totalCount": 1
      },
      "hasReviewPhoto": false,
      "stamps": [],
      "tagDetails": [],
      "promotions": [
        {
          "id": 23749532,
          "name": "300 TL ve Üzeri Kargo Bedava (Satıcı Karşılar)",
          "discountType": 7,
          "shortName": "Kargo Bedava",
          "promotionDiscountType": "Cargo",
          "isTyPlus": false
        }
      ],
      "pricePromotion": null,
      "socialProofs": [
        {
          "type": "basketCount",
          "value": "17",
          "translateKey": "socialProof_basketCount",
          "icon": "https://cdn.dsmcdn.com/mobile/search-result/Socialproof_basketcount.png"
        },
        {
          "type": "orderCountL3D",
          "value": "1",
          "translateKey": "socialProof_orderCountL365D",
          "icon": "https://cdn.dsmcdn.com/web/production/rocket-icon.png"
        },
        {
          "type": "favoriteCount",
          "value": "26",
          "translateKey": "socialProof_favoriteCount",
          "icon": "https://cdn.dsmcdn.com/web/production/orange-heart.png"
        }
      ],
      "lowestPriceDuration": 0,
      "stripBadge": {
        "label": "popular",
        "backgroundColor": "#BB0000",
        "textColor": "#FFFFFF"
      },
      "winnerVariant": {
        "unitInfo": {
          "unitPrice": null,
          "typeName": null,
          "unit": null
        },
        "userSegment": null,
        "discountedPriceInfo": "",
        "listingId": "d1a43f72a1a5aba35b6f9d24010b1911",
        "barcode": "Ms-106",
        "groupTagIds": [],
        "variantAttributes": [
          {
            "attributeName": "Beden",
            "attributeValue": "S"
          }
        ],
        "tagDetails": [],
        "price": {
          "currency": "TRY",
          "buyingPrice": 0,
          "sellingPrice": 699,
          "originalPrice": 699,
          "discountedPrice": 699,
          "profitMargin": 0,
          "rrp": 0,
          "couponApplicablePrice": 699,
          "discountedPriceAfterNoLimitPromotions": 699,
          "tyPlusCouponApplicablePrice": 699
        },
        "rushDeliveryDuration": 24,
        "lowestPriceDuration": {
          "duration": 0
        },
        "itemNumber": 1482110120,
        "quantity": 1000,
        "sellable": true,
        "isWinner": true,
        "freeCargo": true,
        "hasCollectable": true
      },
      "priceChange": "NONE",
      "promotion": [
        {
          "id": 23749532,
          "name": "300 TL ve Üzeri Kargo Bedava (Satıcı Karşılar)",
          "discountType": 7,
          "shortName": "Kargo Bedava",
          "promotionDiscountType": "Cargo",
          "isTyPlus": false
        }
      ],
      "isFlash": false,
      "quantityStatusBadge": {
        "quantity": null,
        "badgeType": null
      }
    },
    {
      "id": 834095544,
      "name": "Lady Büyük Beden Fitness Tayt Crop Sporcu Takımı",
      "inStock": true,
      "brand": {
        "id": 995317,
        "name": "NightLove"
      },
      "webBrand": {
        "id": 995317,
        "name": "NightLove"
      },
      "category": {
        "id": 0,
        "name": ""
      },
      "price": {
        "originalPrice": 599,
        "discountedPrice": 599,
        "oldPrice": 0,
        "sellingPrice": 599,
        "buyingPrice": 599,
        "rrp": 599,
        "pureRrp": 599,
        "favoritedPrice": 0,
        "currency": "TL",
        "originalPriceText": "599,00",
        "discountedPriceText": "599,00",
        "oldPriceText": "0,00",
        "sellingPriceText": "599,00",
        "buyingPriceText": "599,00",
        "rrpText": "599,00"
      },
      "images": [
        "https://cdn.dsmcdn.com/ty1346/product/media/images/prod/QC/20240603/22/17214e3f-107a-36ca-84fb-c1b209e808b3/1_org_zoom.jpg"
      ],
      "imageUrl": "https://cdn.dsmcdn.com/ty1346/product/media/images/prod/QC/20240603/22/17214e3f-107a-36ca-84fb-c1b209e808b3/1_org_zoom.jpg",
      "merchantListings": [
        {
          "promotions": [
            {
              "name": "5 Al 4 Öde",
              "promotionDiscountType": "TwoForOne",
              "shortName": "5 Al 4 Öde",
              "id": 25816714,
              "discountType": 2,
              "isApplied": false,
              "isTyPlus": false
            },
            {
              "name": "300 TL ve Üzeri Kargo Bedava (Satıcı Karşılar)",
              "promotionDiscountType": "Cargo",
              "shortName": "Kargo Bedava",
              "id": 23727722,
              "discountType": 7,
              "isApplied": true,
              "isTyPlus": false
            }
          ],
          "variants": [
            {
              "unitInfo": {
                "unitPrice": null,
                "typeName": null,
                "unit": null
              },
              "userSegment": null,
              "discountedPriceInfo": "",
              "listingId": "a91e81a2bc6fdb44fab8b9935813d6af",
              "barcode": "651231265217",
              "groupTagIds": [],
              "variantAttributes": [
                {
                  "attributeName": "Beden",
                  "attributeValue": "3XL"
                }
              ],
              "tagDetails": [],
              "price": {
                "currency": "TRY",
                "buyingPrice": 0,
                "sellingPrice": 599,
                "originalPrice": 599,
                "discountedPrice": 599,
                "profitMargin": 0,
                "rrp": 0,
                "couponApplicablePrice": 599,
                "discountedPriceAfterNoLimitPromotions": 599,
                "tyPlusCouponApplicablePrice": 599
              },
              "rushDeliveryDuration": 24,
              "lowestPriceDuration": {
                "duration": 0
              },
              "itemNumber": 1119225909,
              "quantity": 94,
              "sellable": true,
              "isWinner": true,
              "freeCargo": true,
              "hasCollectable": false
            }
          ],
          "stamps": [],
          "customValues": [
            {
              "key": "deliveryCountries",
              "value": "AZ"
            },
            {
              "key": "origin",
              "value": "TR"
            }
          ],
          "merchant": {
            "id": 348264
          },
          "isWinner": true,
          "freeCargo": false
        }
      ],
      "recommendedRetailPrice": null,
      "isRunningOut": false,
      "url": "/nightlove/lady-buyuk-beden-fitness-tayt-crop-sporcu-takimi-p-834095544",
      "rating": {
        "averageRating": 4,
        "totalComments": 1
      },
      "ratingScore": {
        "averageRating": 4,
        "totalCount": 1
      },
      "hasReviewPhoto": false,
      "stamps": [],
      "tagDetails": [],
      "promotions": [
        {
          "id": 25816714,
          "name": "5 Al 4 Öde",
          "discountType": 2,
          "shortName": "5 Al 4 Öde",
          "promotionDiscountType": "TwoForOne",
          "isTyPlus": false
        },
        {
          "id": 23727722,
          "name": "300 TL ve Üzeri Kargo Bedava (Satıcı Karşılar)",
          "discountType": 7,
          "shortName": "Kargo Bedava",
          "promotionDiscountType": "Cargo",
          "isTyPlus": false
        }
      ],
      "pricePromotion": null,
      "socialProofs": [
        {
          "type": "basketCount",
          "value": "2",
          "translateKey": "socialProof_basketCount",
          "icon": "https://cdn.dsmcdn.com/mobile/search-result/Socialproof_basketcount.png"
        },
        {
          "type": "orderCountL3D",
          "value": "1",
          "translateKey": "socialProof_orderCountL365D",
          "icon": "https://cdn.dsmcdn.com/web/production/rocket-icon.png"
        },
        {
          "type": "favoriteCount",
          "value": "92",
          "translateKey": "socialProof_favoriteCount",
          "icon": "https://cdn.dsmcdn.com/web/production/orange-heart.png"
        }
      ],
      "lowestPriceDuration": 0,
      "winnerVariant": {
        "unitInfo": {
          "unitPrice": null,
          "typeName": null,
          "unit": null
        },
        "userSegment": null,
        "discountedPriceInfo": "",
        "listingId": "a91e81a2bc6fdb44fab8b9935813d6af",
        "barcode": "651231265217",
        "groupTagIds": [],
        "variantAttributes": [
          {
            "attributeName": "Beden",
            "attributeValue": "3XL"
          }
        ],
        "tagDetails": [],
        "price": {
          "currency": "TRY",
          "buyingPrice": 0,
          "sellingPrice": 599,
          "originalPrice": 599,
          "discountedPrice": 599,
          "profitMargin": 0,
          "rrp": 0,
          "couponApplicablePrice": 599,
          "discountedPriceAfterNoLimitPromotions": 599,
          "tyPlusCouponApplicablePrice": 599
        },
        "rushDeliveryDuration": 24,
        "lowestPriceDuration": {
          "duration": 0
        },
        "itemNumber": 1119225909,
        "quantity": 94,
        "sellable": true,
        "isWinner": true,
        "freeCargo": true,
        "hasCollectable": false
      },
      "priceChange": "NONE",
      "promotion": [
        {
          "id": 25816714,
          "name": "5 Al 4 Öde",
          "discountType": 2,
          "shortName": "5 Al 4 Öde",
          "promotionDiscountType": "TwoForOne",
          "isTyPlus": false
        }
      ],
      "isFlash": false,
      "quantityStatusBadge": {
        "quantity": null,
        "badgeType": null
      }
    }
  ]
}