{
  "category_id": 148076,
  "category_name": "Fotokapan Kamera",
  "total_products": 8,
  "scraped_at": "2025-12-28T20:30:45.689117",
  "products": [
    {
      "id": 346277835,
      "name": "Fotokapan Kamera 16mp Full Hd 1080p Gece Görüşlü 2 Inç Lcd Ekran Su Geçirmez",
      "inStock": true,
      "brand": {
        "id": 988032,
        "name": "JUNGLEE"
      },
      "webBrand": {
        "id": 988032,
        "name": "JUNGLEE"
      },
      "category": {
        "id": 0,
        "name": ""
      },
      "price": {
        "originalPrice": 1389.9,
        "discountedPrice": 1389.9,
        "oldPrice": 0,
        "sellingPrice": 1389.9,
        "buyingPrice": 1389.9,
        "rrp": 1389.9,
        "pureRrp": 1389.9,
        "favoritedPrice": 0,
        "currency": "TL",
        "originalPriceText": "1.389,90",
        "discountedPriceText": "1.389,90",
        "oldPriceText": "0,00",
        "sellingPriceText": "1.389,90",
        "buyingPriceText": "1.389,90",
        "rrpText": "1.389,90"
      },
      "images": [
        "https://cdn.dsmcdn.com/ty815/product/media/images/20230405/18/318847853/554148692/1/1_org_zoom.jpg",
        "https://cdn.dsmcdn.com/ty813/product/media/images/20230405/18/318847853/554148692/2/2_org_zoom.jpg",
        "https://cdn.dsmcdn.com/ty815/product/media/images/20230405/18/318847853/554148692/3/3_org_zoom.jpg",
        "https://cdn.dsmcdn.com/ty813/product/media/images/20230405/18/318847853/554148692/4/4_org_zoom.jpg",
        "https://cdn.dsmcdn.com/ty814/product/media/images/20230405/18/318847853/554148692/5/5_org_zoom.jpg",
        "https://cdn.dsmcdn.com/ty814/product/media/images/20230405/18/318847853/554148692/6/6_org_zoom.jpg",
        "https://cdn.dsmcdn.com/ty814/product/media/images/20230405/18/318847853/554148692/7/7_org_zoom.jpg"
      ],
      "imageUrl": "https://cdn.dsmcdn.com/ty815/product/media/images/20230405/18/318847853/554148692/1/1_org_zoom.jpg",
      "merchantListings": [
        {
          "promotions": [
            {
              "name": "300 TL ve Üzeri Kargo Bedava (Satıcı Karşılar)",
              "promotionDiscountType": "Cargo",
              "shortName": "Kargo Bedava",
              "id": 23677199,
              "discountType": 7,
              "isApplied": true,
              "isTyPlus": false
            }
          ],
          "variants": [
            {
              "unitInfo": {
                "unitPrice": null,
                "typeName": null,
                "unit": null
              },
              "userSegment": null,
              "discountedPriceInfo": "",
              "listingId": "e0f30a8ff5790b28e6c6cb8244260abd",
              "barcode": "JU20220216404",
              "groupTagIds": [],
              "variantAttributes": [],
              "tagDetails": [
                {
                  "tag": "kategori_encoksatanlar",
                  "displayName": "kategori_encoksatanlar",
                  "tagId": 1715,
                  "searchable": true,
                  "priceTagStamp": false,
                  "hasStamp": true
                },
                {
                  "tag": "installment_pft3",
                  "displayName": "Peşin Fiyatına 3 Taksit",
                  "tagId": 4905,
                  "searchable": false,
                  "priceTagStamp": true,
                  "hasStamp": true
                }
              ],
              "price": {
                "currency": "TRY",
                "buyingPrice": 0,
                "sellingPrice": 1389.9,
                "originalPrice": 1389.9,
                "discountedPrice": 1389.9,
                "profitMargin": 0,
                "rrp": 0,
                "couponApplicablePrice": 1389.9,
                "discountedPriceAfterNoLimitPromotions": 1389.9,
                "tyPlusCouponApplicablePrice": 1389.9
              },
              "rushDeliveryDuration": 24,
              "lowestPriceDuration": {
                "duration": 0
              },
              "itemNumber": 554148692,
              "quantity": 359,
              "sellable": true,
              "isWinner": true,
              "freeCargo": true,
              "hasCollectable": false
            }
          ],
          "stamps": [],
          "customValues": [
            {
              "key": "deliveryCountries",
              "value": "AZ"
            },
            {
              "key": "origin",
              "value": "TR"
            }
          ],
          "merchant": {
            "id": 108932
          },
          "isWinner": true,
          "freeCargo": false
        }
      ],
      "recommendedRetailPrice": null,
      "isRunningOut": false,
      "url": "/junglee/fotokapan-kamera-16mp-full-hd-1080p-gece-goruslu-2-inc-lcd-ekran-su-gecirmez-p-346277835",
      "rating": {
        "averageRating": 4.053763440860215,
        "totalComments": 186
      },
      "ratingScore": {
        "averageRating": 4.053763440860215,
        "totalCount": 186
      },
      "hasReviewPhoto": true,
      "stamps": [],
      "tagDetails": [
        {
          "tag": "kategori_encoksatanlar",
          "displayName": "kategori_encoksatanlar",
          "tagId": 1715,
          "searchable": true,
          "priceTagStamp": false,
          "hasStamp": true
        },
        {
          "tag": "installment_pft3",
          "displayName": "Peşin Fiyatına 3 Taksit",
          "tagId": 4905,
          "searchable": false,
          "priceTagStamp": true,
          "hasStamp": true
        }
      ],
      "promotions": [
        {
          "id": 23677199,
          "name": "300 TL ve Üzeri Kargo Bedava (Satıcı Karşılar)",
          "discountType": 7,
          "shortName": "Kargo Bedava",
          "promotionDiscountType": "Cargo",
          "isTyPlus": false
        }
      ],
      "pricePromotion": null,
      "socialProofs": [
        {
          "type": "basketCount",
          "value": "135",
          "translateKey": "socialProof_basketCount",
          "icon": "https://cdn.dsmcdn.com/mobile/search-result/Socialproof_basketcount.png"
        },
        {
          "type": "orderCountL3D",
          "value": "13",
          "translateKey": "socialProof_orderCountL365D",
          "icon": "https://cdn.dsmcdn.com/web/production/rocket-icon.png"
        },
        {
          "type": "favoriteCount",
          "value": "2k",
          "translateKey": "socialProof_favoriteCount",
          "icon": "https://cdn.dsmcdn.com/web/production/orange-heart.png"
        }
      ],
      "lowestPriceDuration": 0,
      "stripBadge": {
        "label": "popular",
        "backgroundColor": "#BB0000",
        "textColor": "#FFFFFF"
      },
      "winnerVariant": {
        "unitInfo": {
          "unitPrice": null,
          "typeName": null,
          "unit": null
        },
        "userSegment": null,
        "discountedPriceInfo": "",
        "listingId": "e0f30a8ff5790b28e6c6cb8244260abd",
        "barcode": "JU20220216404",
        "groupTagIds": [],
        "variantAttributes": [],
        "tagDetails": [
          {
            "tag": "kategori_encoksatanlar",
            "displayName": "kategori_encoksatanlar",
            "tagId": 1715,
            "searchable": true,
            "priceTagStamp": false,
            "hasStamp": true
          },
          {
            "tag": "installment_pft3",
            "displayName": "Peşin Fiyatına 3 Taksit",
            "tagId": 4905,
            "searchable": false,
            "priceTagStamp": true,
            "hasStamp": true
          }
        ],
        "price": {
          "currency": "TRY",
          "buyingPrice": 0,
          "sellingPrice": 1389.9,
          "originalPrice": 1389.9,
          "discountedPrice": 1389.9,
          "profitMargin": 0,
          "rrp": 0,
          "couponApplicablePrice": 1389.9,
          "discountedPriceAfterNoLimitPromotions": 1389.9,
          "tyPlusCouponApplicablePrice": 1389.9
        },
        "rushDeliveryDuration": 24,
        "lowestPriceDuration": {
          "duration": 0
        },
        "itemNumber": 554148692,
        "quantity": 359,
        "sellable": true,
        "isWinner": true,
        "freeCargo": true,
        "hasCollectable": false
      },
      "priceChange": "NONE",
      "promotion": [
        {
          "id": 23677199,
          "name": "300 TL ve Üzeri Kargo Bedava (Satıcı Karşılar)",
          "discountType": 7,
          "shortName": "Kargo Bedava",
          "promotionDiscountType": "Cargo",
          "isTyPlus": false
        }
      ],
      "isFlash": false,
      "quantityStatusBadge": {
        "quantity": null,
        "badgeType": null
      }
    },
    {
      "id": 924384909,
      "name": "850ws Güneş Enerjili Fotokapan 48mp Full Hd Wifi Hareket Sensörlü Gece Görüşlü Ip66 Su Geçirmez",
      "inStock": true,
      "brand": {
        "id": 35029,
        "name": "Juo"
      },
      "webBrand": {
        "id": 35029,
        "name": "Juo"
      },
      "category": {
        "id": 0,
        "name": ""
      },
      "price": {
        "originalPrice": 2488,
        "discountedPrice": 2488,
        "oldPrice": 0,
        "sellingPrice": 2488,
        "buyingPrice": 2488,
        "rrp": 2488,
        "pureRrp": 2488,
        "favoritedPrice": 0,
        "currency": "TL",
        "originalPriceText": "2.488,00",
        "discountedPriceText": "2.488,00",
        "oldPriceText": "0,00",
        "sellingPriceText": "2.488,00",
        "buyingPriceText": "2.488,00",
        "rrpText": "2.488,00"
      },
      "images": [
        "https://cdn.dsmcdn.com/ty1673/prod/QC/20250503/13/1e5565c9-a024-3cb3-b6d2-f6468de328f1/1_org_zoom.jpg",
        "https://cdn.dsmcdn.com/ty1672/prod/QC/20250503/13/df82ff7f-19e5-3294-a9b9-32f7cb643a0c/1_org_zoom.jpg",
        "https://cdn.dsmcdn.com/ty1672/prod/QC/20250503/13/4bacbe71-fac1-3b92-a974-5ec64add7391/1_org_zoom.jpg",
        "https://cdn.dsmcdn.com/ty1673/prod/QC/20250503/13/a219b085-5555-353e-a607-65c997f4b58f/1_org_zoom.jpg",
        "https://cdn.dsmcdn.com/ty1673/prod/QC/20250503/13/e6616aa8-bd26-3008-8cdb-046eda6b00c9/1_org_zoom.jpg",
        "https://cdn.dsmcdn.com/ty1673/prod/QC/20250503/13/0354847b-eb27-30f5-a987-a43d9157b7f1/1_org_zoom.jpg",
        "https://cdn.dsmcdn.com/ty1673/prod/QC/20250503/13/6c294c68-8e97-3a46-9860-639abb0a86b9/1_org_zoom.jpg",
        "https://cdn.dsmcdn.com/ty1673/prod/QC/20250503/13/2713cb9a-cd71-3d7d-9196-99a82c439c58/1_org_zoom.jpg"
      ],
      "imageUrl": "https://cdn.dsmcdn.com/ty1673/prod/QC/20250503/13/1e5565c9-a024-3cb3-b6d2-f6468de328f1/1_org_zoom.jpg",
      "merchantListings": [
        {
          "promotions": [
            {
              "name": "300 TL ve Üzeri Kargo Bedava (Satıcı Karşılar)",
              "promotionDiscountType": "Cargo",
              "shortName": "Kargo Bedava",
              "id": 23641583,
              "discountType": 7,
              "isApplied": true,
              "isTyPlus": false
            }
          ],
          "variants": [
            {
              "unitInfo": {
                "unitPrice": null,
                "typeName": null,
                "unit": null
              },
              "userSegment": null,
              "discountedPriceInfo": "",
              "listingId": "3a99f3a406693d9c62a373aca3661235",
              "barcode": "8682035613039",
              "groupTagIds": [
                "ebb03b49-5399-4c1c-902e-f2f979d1088b"
              ],
              "variantAttributes": [],
              "tagDetails": [
                {
                  "tag": "beyaz_kampanya_urunu",
                  "displayName": "Beyaz Kampanya Ürünü",
                  "tagId": 1,
                  "searchable": false,
                  "priceTagStamp": true,
                  "hasStamp": false
                },
                {
                  "tag": "installment_pft3",
                  "displayName": "Peşin Fiyatına 3 Taksit",
                  "tagId": 4905,
                  "searchable": false,
                  "priceTagStamp": true,
                  "hasStamp": true
                }
              ],
              "price": {
                "currency": "TRY",
                "buyingPrice": 0,
                "sellingPrice": 2488,
                "originalPrice": 2488,
                "discountedPrice": 2488,
                "profitMargin": 0,
                "rrp": 0,
                "couponApplicablePrice": 2488,
                "discountedPriceAfterNoLimitPromotions": 2488,
                "tyPlusCouponApplicablePrice": 2488
              },
              "rushDeliveryDuration": 24,
              "lowestPriceDuration": {
                "duration": 0
              },
              "itemNumber": 1305933958,
              "quantity": 77,
              "sellable": true,
              "isWinner": true,
              "freeCargo": true,
              "hasCollectable": false
            }
          ],
          "stamps": [],
          "customValues": [
            {
              "key": "deliveryCountries",
              "value": "AZ"
            },
            {
              "key": "origin",
              "value": "CN"
            }
          ],
          "merchant": {
            "id": 252249
          },
          "isWinner": true,
          "freeCargo": true
        }
      ],
      "recommendedRetailPrice": null,
      "isRunningOut": false,
      "url": "/juo/850ws-gunes-enerjili-fotokapan-48mp-full-hd-wifi-hareket-sensorlu-gece-goruslu-ip66-su-gecirmez-p-924384909",
      "rating": {
        "averageRating": 4.285714285714286,
        "totalComments": 7
      },
      "ratingScore": {
        "averageRating": 4.285714285714286,
        "totalCount": 7
      },
      "hasReviewPhoto": true,
      "stamps": [],
      "tagDetails": [
        {
          "tag": "beyaz_kampanya_urunu",
          "displayName": "Beyaz Kampanya Ürünü",
          "tagId": 1,
          "searchable": false,
          "priceTagStamp": true,
          "hasStamp": false
        },
        {
          "tag": "installment_pft3",
          "displayName": "Peşin Fiyatına 3 Taksit",
          "tagId": 4905,
          "searchable": false,
          "priceTagStamp": true,
          "hasStamp": true
        }
      ],
      "promotions": [
        {
          "id": 23641583,
          "name": "300 TL ve Üzeri Kargo Bedava (Satıcı Karşılar)",
          "discountType": 7,
          "shortName": "Kargo Bedava",
          "promotionDiscountType": "Cargo",
          "isTyPlus": false
        }
      ],
      "pricePromotion": null,
      "socialProofs": [
        {
          "type": "basketCount",
          "value": "47",
          "translateKey": "socialProof_basketCount",
          "icon": "https://cdn.dsmcdn.com/mobile/search-result/Socialproof_basketcount.png"
        },
        {
          "type": "orderCountL3D",
          "value": "3",
          "translateKey": "socialProof_orderCountL365D",
          "icon": "https://cdn.dsmcdn.com/web/production/rocket-icon.png"
        },
        {
          "type": "favoriteCount",
          "value": "135",
          "translateKey": "socialProof_favoriteCount",
          "icon": "https://cdn.dsmcdn.com/web/production/orange-heart.png"
        }
      ],
      "lowestPriceDuration": 0,
      "stripBadge": {
        "label": "popular",
        "backgroundColor": "#BB0000",
        "textColor": "#FFFFFF"
      },
      "winnerVariant": {
        "unitInfo": {
          "unitPrice": null,
          "typeName": null,
          "unit": null
        },
        "userSegment": null,
        "discountedPriceInfo": "",
        "listingId": "3a99f3a406693d9c62a373aca3661235",
        "barcode": "8682035613039",
        "groupTagIds": [
          "ebb03b49-5399-4c1c-902e-f2f979d1088b"
        ],
        "variantAttributes": [],
        "tagDetails": [
          {
            "tag": "beyaz_kampanya_urunu",
            "displayName": "Beyaz Kampanya Ürünü",
            "tagId": 1,
            "searchable": false,
            "priceTagStamp": true,
            "hasStamp": false
          },
          {
            "tag": "installment_pft3",
            "displayName": "Peşin Fiyatına 3 Taksit",
            "tagId": 4905,
            "searchable": false,
            "priceTagStamp": true,
            "hasStamp": true
          }
        ],
        "price": {
          "currency": "TRY",
          "buyingPrice": 0,
          "sellingPrice": 2488,
          "originalPrice": 2488,
          "discountedPrice": 2488,
          "profitMargin": 0,
          "rrp": 0,
          "couponApplicablePrice": 2488,
          "discountedPriceAfterNoLimitPromotions": 2488,
          "tyPlusCouponApplicablePrice": 2488
        },
        "rushDeliveryDuration": 24,
        "lowestPriceDuration": {
          "duration": 0
        },
        "itemNumber": 1305933958,
        "quantity": 77,
        "sellable": true,
        "isWinner": true,
        "freeCargo": true,
        "hasCollectable": false
      },
      "priceChange": "NONE",
      "promotion": [
        {
          "id": 23641583,
          "name": "300 TL ve Üzeri Kargo Bedava (Satıcı Karşılar)",
          "discountType": 7,
          "shortName": "Kargo Bedava",
          "promotionDiscountType": "Cargo",
          "isTyPlus": false
        }
      ],
      "isFlash": false,
      "quantityStatusBadge": {
        "quantity": null,
        "badgeType": null
      }
    },
    {
      "id": 1019684421,
      "name": "X60P 48 Mp Gsm Destekli Fotokapan",
      "inStock": true,
      "brand": {
        "id": 2791215,
        "name": "GardePro"
      },
      "webBrand": {
        "id": 2791215,
        "name": "GardePro"
      },
      "category": {
        "id": 0,
        "name": ""
      },
      "price": {
        "originalPrice": 10069.05,
        "discountedPrice": 10069.05,
        "oldPrice": 10599,
        "sellingPrice": 10069.05,
        "buyingPrice": 10069.05,
        "rrp": 10069.05,
        "pureRrp": 10069.05,
        "favoritedPrice": 0,
        "currency": "TL",
        "originalPriceText": "10.069,05",
        "discountedPriceText": "10.069,05",
        "oldPriceText": "10.599,00",
        "sellingPriceText": "10.069,05",
        "buyingPriceText": "10.069,05",
        "rrpText": "10.069,05"
      },
      "images": [
        "https://cdn.dsmcdn.com/ty1767/prod/QC_PREP/20251009/14/89a219d6-9e84-36a2-9f04-eafa49e525f6/1_org_zoom.jpg",
        "https://cdn.dsmcdn.com/ty1767/prod/QC_PREP/20251009/14/aa207409-ca48-3bdb-af70-6a22ef712c31/1_org_zoom.jpg",
        "https://cdn.dsmcdn.com/ty1767/prod/QC_PREP/20251009/14/a5be5c01-b1bc-372e-9afa-65c91a47676e/1_org_zoom.jpg",
        "https://cdn.dsmcdn.com/ty1767/prod/QC_PREP/20251009/14/fc6e3645-a78d-3171-a7df-f65123172bfe/1_org_zoom.jpg",
        "https://cdn.dsmcdn.com/ty1767/prod/QC_PREP/20251009/14/f9894712-943a-3472-aa86-2cc12a34efdc/1_org_zoom.jpg",
        "https://cdn.dsmcdn.com/ty1769/prod/QC_PREP/20251009/14/9226a612-531c-3f1c-8cc8-fa8b47848a7e/1_org_zoom.jpg",
        "https://cdn.dsmcdn.com/ty1769/prod/QC_PREP/20251009/14/286b0cec-4db1-306d-96cc-ea991286a63d/1_org_zoom.jpg"
      ],
      "imageUrl": "https://cdn.dsmcdn.com/ty1767/prod/QC_PREP/20251009/14/89a219d6-9e84-36a2-9f04-eafa49e525f6/1_org_zoom.jpg",
      "merchantListings": [
        {
          "promotions": [
            {
              "name": "Sepette %5 İndirim",
              "promotionDiscountType": "DiscountOnBasket",
              "shortName": "",
              "id": 25768270,
              "discountType": 2,
              "isApplied": true,
              "isTyPlus": false
            },
            {
              "name": "300 TL ve Üzeri Kargo Bedava (Satıcı Karşılar)",
              "promotionDiscountType": "Cargo",
              "shortName": "Kargo Bedava",
              "id": 25010940,
              "discountType": 7,
              "isApplied": true,
              "isTyPlus": false
            }
          ],
          "variants": [
            {
              "unitInfo": {
                "unitPrice": null,
                "typeName": null,
                "unit": null
              },
              "userSegment": null,
              "discountedPriceInfo": "",
              "listingId": "7f6216c9780464e9a64e87bffc408922",
              "barcode": "HOG1000",
              "groupTagIds": [],
              "variantAttributes": [],
              "tagDetails": [
                {
                  "tag": "installment_pft3",
                  "displayName": "Peşin Fiyatına 3 Taksit",
                  "tagId": 4905,
                  "searchable": false,
                  "priceTagStamp": true,
                  "hasStamp": true
                }
              ],
              "price": {
                "currency": "TRY",
                "buyingPrice": 0,
                "sellingPrice": 10599,
                "originalPrice": 10069.05,
                "discountedPrice": 10069.05,
                "profitMargin": 0,
                "rrp": 0,
                "couponApplicablePrice": 10069.05,
                "discountedPriceAfterNoLimitPromotions": 10069.05,
                "tyPlusCouponApplicablePrice": 10069.05
              },
              "rushDeliveryDuration": 0,
              "lowestPriceDuration": {
                "duration": 0
              },
              "itemNumber": 1415073913,
              "quantity": 3,
              "sellable": true,
              "isWinner": true,
              "freeCargo": true,
              "hasCollectable": false
            }
          ],
          "stamps": [],
          "customValues": [
            {
              "key": "deliveryCountries",
              "value": "AZ"
            }
          ],
          "merchant": {
            "id": 1152764
          },
          "isWinner": true,
          "freeCargo": false
        }
      ],
      "recommendedRetailPrice": null,
      "isRunningOut": false,
      "url": "/gardepro/x60p-48-mp-gsm-destekli-fotokapan-p-1019684421",
      "rating": {
        "averageRating": 3,
        "totalComments": 2
      },
      "ratingScore": {
        "averageRating": 3,
        "totalCount": 2
      },
      "hasReviewPhoto": true,
      "stamps": [],
      "tagDetails": [
        {
          "tag": "installment_pft3",
          "displayName": "Peşin Fiyatına 3 Taksit",
          "tagId": 4905,
          "searchable": false,
          "priceTagStamp": true,
          "hasStamp": true
        }
      ],
      "promotions": [
        {
          "id": 25768270,
          "name": "Sepette %5 İndirim",
          "discountType": 2,
          "shortName": "Sepette %5 İndirim",
          "promotionDiscountType": "DiscountOnBasket",
          "isTyPlus": false
        },
        {
          "id": 25010940,
          "name": "300 TL ve Üzeri Kargo Bedava (Satıcı Karşılar)",
          "discountType": 7,
          "shortName": "Kargo Bedava",
          "promotionDiscountType": "Cargo",
          "isTyPlus": false
        }
      ],
      "pricePromotion": null,
      "socialProofs": [
        {
          "type": "basketCount",
          "value": "11",
          "translateKey": "socialProof_basketCount",
          "icon": "https://cdn.dsmcdn.com/mobile/search-result/Socialproof_basketcount.png"
        },
        {
          "type": "orderCountL3D",
          "value": "2",
          "translateKey": "socialProof_orderCountL365D",
          "icon": "https://cdn.dsmcdn.com/web/production/rocket-icon.png"
        },
        {
          "type": "favoriteCount",
          "value": "27",
          "translateKey": "socialProof_favoriteCount",
          "icon": "https://cdn.dsmcdn.com/web/production/orange-heart.png"
        }
      ],
      "lowestPriceDuration": 0,
      "stripBadge": {
        "label": "rank_increased",
        "value": 1,
        "icon": "https://cdn.dsmcdn.com/sfint/prod/fp/up-list_1760345139449.png",
        "backgroundColor": "#0BC15C",
        "textColor": "#FFFFFF"
      },
      "winnerVariant": {
        "unitInfo": {
          "unitPrice": null,
          "typeName": null,
          "unit": null
        },
        "userSegment": null,
        "discountedPriceInfo": "",
        "listingId": "7f6216c9780464e9a64e87bffc408922",
        "barcode": "HOG1000",
        "groupTagIds": [],
        "variantAttributes": [],
        "tagDetails": [
          {
            "tag": "installment_pft3",
            "displayName": "Peşin Fiyatına 3 Taksit",
            "tagId": 4905,
            "searchable": false,
            "priceTagStamp": true,
            "hasStamp": true
          }
        ],
        "price": {
          "currency": "TRY",
          "buyingPrice": 0,
          "sellingPrice": 10599,
          "originalPrice": 10069.05,
          "discountedPrice": 10069.05,
          "profitMargin": 0,
          "rrp": 0,
          "couponApplicablePrice": 10069.05,
          "discountedPriceAfterNoLimitPromotions": 10069.05,
          "tyPlusCouponApplicablePrice": 10069.05
        },
        "rushDeliveryDuration": 0,
        "lowestPriceDuration": {
          "duration": 0
        },
        "itemNumber": 1415073913,
        "quantity": 3,
        "sellable": true,
        "isWinner": true,
        "freeCargo": true,
        "hasCollectable": false
      },
      "priceChange": "NONE",
      "promotion": [
        {
          "id": 25768270,
          "name": "Sepette %5 İndirim",
          "discountType": 2,
          "shortName": "Sepette %5 İndirim",
          "promotionDiscountType": "DiscountOnBasket",
          "isTyPlus": false
        }
      ],
      "isFlash": false,
      "quantityStatusBadge": {
        "quantity": 3,
        "badgeType": "LAST_X_ITEMS"
      }
    },
    {
      "id": 636523401,
      "name": "Fotokapan Kamera 16mp Full Hd 1080p Gece Görüşlü 2 Inç Lcd Ekran Su Geçirmez Trail Camera",
      "inStock": true,
      "brand": {
        "id": 988032,
        "name": "JUNGLEE"
      },
      "webBrand": {
        "id": 988032,
        "name": "JUNGLEE"
      },
      "category": {
        "id": 0,
        "name": ""
      },
      "price": {
        "originalPrice": 1216.66,
        "discountedPrice": 1158.15,
        "oldPrice": 1216.66,
        "sellingPrice": 1158.15,
        "buyingPrice": 1158.15,
        "rrp": 1216.66,
        "pureRrp": 1216.66,
        "favoritedPrice": 0,
        "currency": "TL",
        "originalPriceText": "1.216,66",
        "discountedPriceText": "1.158,15",
        "oldPriceText": "1.216,66",
        "sellingPriceText": "1.158,15",
        "buyingPriceText": "1.158,15",
        "rrpText": "1.216,66"
      },
      "images": [
        "https://cdn.dsmcdn.com/ty1217/product/media/images/prod/SPM/PIM/20240319/17/6fbf26a6-9ec4-3e40-b08c-bc1ae3e333d7/1_org_zoom.jpg",
        "https://cdn.dsmcdn.com/ty1216/product/media/images/prod/SPM/PIM/20240319/17/9693ef62-5c72-36de-8cbf-0588abd8ffe1/1_org_zoom.jpg",
        "https://cdn.dsmcdn.com/ty1215/product/media/images/prod/SPM/PIM/20240319/17/21562c5f-3d06-370c-976a-ade1a9468055/1_org_zoom.jpg",
        "https://cdn.dsmcdn.com/ty1217/product/media/images/prod/SPM/PIM/20240319/17/39e359e6-b94f-3d8f-9eaa-8bbb749d2300/1_org_zoom.jpg",
        "https://cdn.dsmcdn.com/ty1217/product/media/images/prod/SPM/PIM/20240319/17/b3363f67-cfeb-3bc3-a539-b6f64061dd44/1_org_zoom.jpg",
        "https://cdn.dsmcdn.com/ty1216/product/media/images/prod/SPM/PIM/20240319/17/1caf3a38-0baf-3a15-a2dc-951ae267cc0d/1_org_zoom.jpg",
        "https://cdn.dsmcdn.com/ty1217/product/media/images/prod/SPM/PIM/20240319/17/32860a58-0a1e-39b4-b940-5f69d59fb6bd/1_org_zoom.jpg",
        "https://cdn.dsmcdn.com/ty1215/product/media/images/prod/SPM/PIM/20240319/17/1200184f-e344-3b97-9605-94e4c43a94eb/1_org_zoom.jpg"
      ],
      "imageUrl": "https://cdn.dsmcdn.com/ty1217/product/media/images/prod/SPM/PIM/20240319/17/6fbf26a6-9ec4-3e40-b08c-bc1ae3e333d7/1_org_zoom.jpg",
      "merchantListings": [
        {
          "promotions": [
            {
              "name": "1500 TL'ye 30 TL İndirim",
              "promotionDiscountType": "DiscountOnBasket",
              "shortName": "Çok Al Az Öde",
              "id": 25747664,
              "discountType": 2,
              "isApplied": false,
              "isTyPlus": false
            },
            {
              "name": "2. Ürüne 50 TL İndirim",
              "promotionDiscountType": "TwoForOne",
              "shortName": "Çok Al Az Öde",
              "id": 25747672,
              "discountType": 2,
              "isApplied": false,
              "isTyPlus": false
            },
            {
              "name": "300 TL ve Üzeri Kargo Bedava (Satıcı Karşılar)",
              "promotionDiscountType": "Cargo",
              "shortName": "Kargo Bedava",
              "id": 23754779,
              "discountType": 7,
              "isApplied": true,
              "isTyPlus": false
            }
          ],
          "variants": [
            {
              "unitInfo": {
                "unitPrice": null,
                "typeName": null,
                "unit": null
              },
              "userSegment": null,
              "discountedPriceInfo": "",
              "listingId": "044ec214b54dfe77d1cfbae9679ad9ae",
              "barcode": "hk30089471065845615",
              "groupTagIds": [
                "ebb03b49-5399-4c1c-902e-f2f979d1088b"
              ],
              "variantAttributes": [],
              "tagDetails": [
                {
                  "tag": "sari_kampanya_urunu",
                  "displayName": "Avantajlı Ürün",
                  "tagId": 4897,
                  "searchable": true,
                  "priceTagStamp": true,
                  "hasStamp": true
                },
                {
                  "tag": "installment_pft3",
                  "displayName": "Peşin Fiyatına 3 Taksit",
                  "tagId": 4905,
                  "searchable": false,
                  "priceTagStamp": true,
                  "hasStamp": true
                },
                {
                  "tag": "lowest_price",
                  "displayName": "",
                  "tagId": 1,
                  "searchable": true,
                  "priceTagStamp": true,
                  "hasStamp": false
                },
                {
                  "tag": "lowest_price_duration_14",
                  "displayName": "Son 14 Günün En Düşük Fiyatı",
                  "tagId": 7590,
                  "searchable": true,
                  "priceTagStamp": true,
                  "hasStamp": true
                },
                {
                  "tag": "eventdeal",
                  "displayName": "",
                  "tagId": 1,
                  "searchable": false,
                  "priceTagStamp": true,
                  "hasStamp": false
                }
              ],
              "price": {
                "currency": "TRY",
                "buyingPrice": 0,
                "sellingPrice": 1158.15,
                "originalPrice": 1216.66,
                "discountedPrice": 1158.15,
                "profitMargin": 0,
                "rrp": 0,
                "couponApplicablePrice": 1158.15,
                "discountedPriceAfterNoLimitPromotions": 1158.15,
                "tyPlusCouponApplicablePrice": 1158.15
              },
              "rushDeliveryDuration": 24,
              "lowestPriceDuration": {
                "duration": 14
              },
              "itemNumber": 841239918,
              "quantity": 953,
              "sellable": true,
              "isWinner": true,
              "freeCargo": true,
              "hasCollectable": false
            }
          ],
          "stamps": [],
          "customValues": [
            {
              "key": "deliveryCountries",
              "value": "AZ"
            },
            {
              "key": "origin",
              "value": "TR"
            }
          ],
          "merchant": {
            "id": 747032
          },
          "isWinner": true,
          "freeCargo": true
        }
      ],
      "recommendedRetailPrice": null,
      "isRunningOut": false,
      "url": "/junglee/fotokapan-kamera-16mp-full-hd-1080p-gece-goruslu-2-inc-lcd-ekran-su-gecirmez-trail-camera-p-636523401",
      "rating": {
        "averageRating": 3.8666666666666667,
        "totalComments": 15
      },
      "ratingScore": {
        "averageRating": 3.8666666666666667,
        "totalCount": 15
      },
      "hasReviewPhoto": false,
      "stamps": [],
      "tagDetails": [
        {
          "tag": "sari_kampanya_urunu",
          "displayName": "Avantajlı Ürün",
          "tagId": 4897,
          "searchable": true,
          "priceTagStamp": true,
          "hasStamp": true
        },
        {
          "tag": "installment_pft3",
          "displayName": "Peşin Fiyatına 3 Taksit",
          "tagId": 4905,
          "searchable": false,
          "priceTagStamp": true,
          "hasStamp": true
        },
        {
          "tag": "lowest_price",
          "displayName": "",
          "tagId": 1,
          "searchable": true,
          "priceTagStamp": true,
          "hasStamp": false
        },
        {
          "tag": "lowest_price_duration_14",
          "displayName": "Son 14 Günün En Düşük Fiyatı",
          "tagId": 7590,
          "searchable": true,
          "priceTagStamp": true,
          "hasStamp": true
        },
        {
          "tag": "eventdeal",
          "displayName": "",
          "tagId": 1,
          "searchable": false,
          "priceTagStamp": true,
          "hasStamp": false
        }
      ],
      "promotions": [
        {
          "id": 25747664,
          "name": "1500 TL'ye 30 TL İndirim",
          "discountType": 2,
          "shortName": "Çok Al Az Öde",
          "promotionDiscountType": "DiscountOnBasket",
          "isTyPlus": false
        },
        {
          "id": 25747672,
          "name": "2. Ürüne 50 TL İndirim",
          "discountType": 2,
          "shortName": "Çok Al Az Öde",
          "promotionDiscountType": "TwoForOne",
          "isTyPlus": false
        },
        {
          "id": 23754779,
          "name": "300 TL ve Üzeri Kargo Bedava (Satıcı Karşılar)",
          "discountType": 7,
          "shortName": "Kargo Bedava",
          "promotionDiscountType": "Cargo",
          "isTyPlus": false
        }
      ],
      "pricePromotion": null,
      "socialProofs": [
        {
          "type": "basketCount",
          "value": "28",
          "translateKey": "socialProof_basketCount",
          "icon": "https://cdn.dsmcdn.com/mobile/search-result/Socialproof_basketcount.png"
        },
        {
          "type": "orderCountL3D",
          "value": "2",
          "translateKey": "socialProof_orderCountL365D",
          "icon": "https://cdn.dsmcdn.com/web/production/rocket-icon.png"
        },
        {
          "type": "favoriteCount",
          "value": "237",
          "translateKey": "socialProof_favoriteCount",
          "icon": "https://cdn.dsmcdn.com/web/production/orange-heart.png"
        }
      ],
      "lowestPriceDuration": 14,
      "stripBadge": {
        "label": "popular",
        "backgroundColor": "#BB0000",
        "textColor": "#FFFFFF"
      },
      "winnerVariant": {
        "unitInfo": {
          "unitPrice": null,
          "typeName": null,
          "unit": null
        },
        "userSegment": null,
        "discountedPriceInfo": "",
        "listingId": "044ec214b54dfe77d1cfbae9679ad9ae",
        "barcode": "hk30089471065845615",
        "groupTagIds": [
          "ebb03b49-5399-4c1c-902e-f2f979d1088b"
        ],
        "variantAttributes": [],
        "tagDetails": [
          {
            "tag": "sari_kampanya_urunu",
            "displayName": "Avantajlı Ürün",
            "tagId": 4897,
            "searchable": true,
            "priceTagStamp": true,
            "hasStamp": true
          },
          {
            "tag": "installment_pft3",
            "displayName": "Peşin Fiyatına 3 Taksit",
            "tagId": 4905,
            "searchable": false,
            "priceTagStamp": true,
            "hasStamp": true
          },
          {
            "tag": "lowest_price",
            "displayName": "",
            "tagId": 1,
            "searchable": true,
            "priceTagStamp": true,
            "hasStamp": false
          },
          {
            "tag": "lowest_price_duration_14",
            "displayName": "Son 14 Günün En Düşük Fiyatı",
            "tagId": 7590,
            "searchable": true,
            "priceTagStamp": true,
            "hasStamp": true
          },
          {
            "tag": "eventdeal",
            "displayName": "",
            "tagId": 1,
            "searchable": false,
            "priceTagStamp": true,
            "hasStamp": false
          }
        ],
        "price": {
          "currency": "TRY",
          "buyingPrice": 0,
          "sellingPrice": 1158.15,
          "originalPrice": 1216.66,
          "discountedPrice": 1158.15,
          "profitMargin": 0,
          "rrp": 0,
          "couponApplicablePrice": 1158.15,
          "discountedPriceAfterNoLimitPromotions": 1158.15,
          "tyPlusCouponApplicablePrice": 1158.15
        },
        "rushDeliveryDuration": 24,
        "lowestPriceDuration": {
          "duration": 14
        },
        "itemNumber": 841239918,
        "quantity": 953,
        "sellable": true,
        "isWinner": true,
        "freeCargo": true,
        "hasCollectable": false
      },
      "priceChange": "NONE",
      "promotion": [
        {
          "id": 25747664,
          "name": "1500 TL'ye 30 TL İndirim",
          "discountType": 2,
          "shortName": "Çok Al Az Öde",
          "promotionDiscountType": "DiscountOnBasket",
          "isTyPlus": false
        }
      ],
      "isFlash": false,
      "quantityStatusBadge": {
        "quantity": null,
        "badgeType": null
      }
    },
    {
      "id": 871082447,
      "name": "FOTO KAPAN AVENIR GÜNEŞ ENERJİLİ SİM KARTLI",
      "inStock": true,
      "brand": {
        "id": 392251,
        "name": "AVENİR"
      },
      "webBrand": {
        "id": 392251,
        "name": "AVENİR"
      },
      "category": {
        "id": 0,
        "name": ""
      },
      "price": {
        "originalPrice": 6000,
        "discountedPrice": 6000,
        "oldPrice": 0,
        "sellingPrice": 6000,
        "buyingPrice": 6000,
        "rrp": 6000,
        "pureRrp": 6000,
        "favoritedPrice": 0,
        "currency": "TL",
        "originalPriceText": "6.000,00",
        "discountedPriceText": "6.000,00",
        "oldPriceText": "0,00",
        "sellingPriceText": "6.000,00",
        "buyingPriceText": "6.000,00",
        "rrpText": "6.000,00"
      },
      "images": [
        "https://cdn.dsmcdn.com/ty1689/prod/QC_ENRICHMENT/20250611/10/f78858f1-d583-3fee-8421-8fb61bab825f/1_org_zoom.jpg",
        "https://cdn.dsmcdn.com/ty1690/prod/QC_ENRICHMENT/20250611/10/30bf60e5-80d1-31d6-a48f-35ab1df7a19c/1_org_zoom.jpg",
        "https://cdn.dsmcdn.com/ty1689/prod/QC_ENRICHMENT/20250611/10/db417f64-616e-3b2d-bc05-75edfb9a1f94/1_org_zoom.jpg",
        "https://cdn.dsmcdn.com/ty1691/prod/QC_ENRICHMENT/20250611/10/84cfefc4-97e4-3f7e-a60f-7c441b445a89/1_org_zoom.jpg",
        "https://cdn.dsmcdn.com/ty1691/prod/QC_ENRICHMENT/20250611/10/bb61ed99-43a4-3e22-a01d-36917869ddf7/1_org_zoom.jpg",
        "https://cdn.dsmcdn.com/ty1689/prod/QC_ENRICHMENT/20250611/10/08968f52-264a-3e4d-be3e-703f6ea42047/1_org_zoom.jpg",
        "https://cdn.dsmcdn.com/ty1689/prod/QC_ENRICHMENT/20250611/10/ae58b776-07c0-35d6-a798-ff2ccb04c047/1_org_zoom.jpg"
      ],
      "imageUrl": "https://cdn.dsmcdn.com/ty1689/prod/QC_ENRICHMENT/20250611/10/f78858f1-d583-3fee-8421-8fb61bab825f/1_org_zoom.jpg",
      "merchantListings": [
        {
          "promotions": [
            {
              "name": "300 TL ve Üzeri Kargo Bedava (Satıcı Karşılar)",
              "promotionDiscountType": "Cargo",
              "shortName": "Kargo Bedava",
              "id": 23681516,
              "discountType": 7,
              "isApplied": true,
              "isTyPlus": false
            }
          ],
          "variants": [
            {
              "unitInfo": {
                "unitPrice": null,
                "typeName": null,
                "unit": null
              },
              "userSegment": null,
              "discountedPriceInfo": "",
              "listingId": "27a24867b0dcfe5d952dfa77ad7be930",
              "barcode": "AVS440H",
              "groupTagIds": [],
              "variantAttributes": [],
              "tagDetails": [
                {
                  "tag": "installment_pft3",
                  "displayName": "Peşin Fiyatına 3 Taksit",
                  "tagId": 4905,
                  "searchable": false,
                  "priceTagStamp": true,
                  "hasStamp": true
                }
              ],
              "price": {
                "currency": "TRY",
                "buyingPrice": 0,
                "sellingPrice": 6000,
                "originalPrice": 6000,
                "discountedPrice": 6000,
                "profitMargin": 0,
                "rrp": 0,
                "couponApplicablePrice": 6000,
                "discountedPriceAfterNoLimitPromotions": 6000,
                "tyPlusCouponApplicablePrice": 6000
              },
              "rushDeliveryDuration": 24,
              "lowestPriceDuration": {
                "duration": 0
              },
              "itemNumber": 1188707463,
              "quantity": 19,
              "sellable": true,
              "isWinner": true,
              "freeCargo": true,
              "hasCollectable": false
            }
          ],
          "stamps": [],
          "customValues": [
            {
              "key": "deliveryCountries",
              "value": "AZ"
            },
            {
              "key": "origin",
              "value": "TR"
            }
          ],
          "merchant": {
            "id": 780083
          },
          "isWinner": true,
          "freeCargo": false
        }
      ],
      "recommendedRetailPrice": null,
      "isRunningOut": false,
      "url": "/avenir/foto-kapan-avenir-gunes-enerjili-sim-kartli-p-871082447",
      "rating": {
        "averageRating": 3.6666666666666665,
        "totalComments": 6
      },
      "ratingScore": {
        "averageRating": 3.6666666666666665,
        "totalCount": 6
      },
      "hasReviewPhoto": false,
      "stamps": [],
      "tagDetails": [
        {
          "tag": "installment_pft3",
          "displayName": "Peşin Fiyatına 3 Taksit",
          "tagId": 4905,
          "searchable": false,
          "priceTagStamp": true,
          "hasStamp": true
        }
      ],
      "promotions": [
        {
          "id": 23681516,
          "name": "300 TL ve Üzeri Kargo Bedava (Satıcı Karşılar)",
          "discountType": 7,
          "shortName": "Kargo Bedava",
          "promotionDiscountType": "Cargo",
          "isTyPlus": false
        }
      ],
      "pricePromotion": null,
      "socialProofs": [
        {
          "type": "basketCount",
          "value": "17",
          "translateKey": "socialProof_basketCount",
          "icon": "https://cdn.dsmcdn.com/mobile/search-result/Socialproof_basketcount.png"
        },
        {
          "type": "orderCountL3D",
          "value": "1",
          "translateKey": "socialProof_orderCountL365D",
          "icon": "https://cdn.dsmcdn.com/web/production/rocket-icon.png"
        },
        {
          "type": "favoriteCount",
          "value": "234",
          "translateKey": "socialProof_favoriteCount",
          "icon": "https://cdn.dsmcdn.com/web/production/orange-heart.png"
        }
      ],
      "lowestPriceDuration": 0,
      "stripBadge": {
        "label": "rank_increased",
        "value": 3,
        "icon": "https://cdn.dsmcdn.com/sfint/prod/fp/up-list_1760345139449.png",
        "backgroundColor": "#0BC15C",
        "textColor": "#FFFFFF"
      },
      "winnerVariant": {
        "unitInfo": {
          "unitPrice": null,
          "typeName": null,
          "unit": null
        },
        "userSegment": null,
        "discountedPriceInfo": "",
        "listingId": "27a24867b0dcfe5d952dfa77ad7be930",
        "barcode": "AVS440H",
        "groupTagIds": [],
        "variantAttributes": [],
        "tagDetails": [
          {
            "tag": "installment_pft3",
            "displayName": "Peşin Fiyatına 3 Taksit",
            "tagId": 4905,
            "searchable": false,
            "priceTagStamp": true,
            "hasStamp": true
          }
        ],
        "price": {
          "currency": "TRY",
          "buyingPrice": 0,
          "sellingPrice": 6000,
          "originalPrice": 6000,
          "discountedPrice": 6000,
          "profitMargin": 0,
          "rrp": 0,
          "couponApplicablePrice": 6000,
          "discountedPriceAfterNoLimitPromotions": 6000,
          "tyPlusCouponApplicablePrice": 6000
        },
        "rushDeliveryDuration": 24,
        "lowestPriceDuration": {
          "duration": 0
        },
        "itemNumber": 1188707463,
        "quantity": 19,
        "sellable": true,
        "isWinner": true,
        "freeCargo": true,
        "hasCollectable": false
      },
      "priceChange": "NONE",
      "promotion": [
        {
          "id": 23681516,
          "name": "300 TL ve Üzeri Kargo Bedava (Satıcı Karşılar)",
          "discountType": 7,
          "shortName": "Kargo Bedava",
          "promotionDiscountType": "Cargo",
          "isTyPlus": false
        }
      ],
      "isFlash": false,
      "quantityStatusBadge": {
        "quantity": null,
        "badgeType": "RUNNING_OUT"
      }
    },
    {
      "id": 871121751,
      "name": "Fotokapan Kamera 16mp Full Hd 1080p Gece Görüşlü 2 Inç Lcd Ekran Su Geçirmez Avcı Doğa Kamerası",
      "inStock": true,
      "brand": {
        "id": 41287,
        "name": "Tastech"
      },
      "webBrand": {
        "id": 41287,
        "name": "Tastech"
      },
      "category": {
        "id": 0,
        "name": ""
      },
      "price": {
        "originalPrice": 1499,
        "discountedPrice": 1499,
        "oldPrice": 0,
        "sellingPrice": 1499,
        "buyingPrice": 1499,
        "rrp": 1499,
        "pureRrp": 1499,
        "favoritedPrice": 0,
        "currency": "TL",
        "originalPriceText": "1.499,00",
        "discountedPriceText": "1.499,00",
        "oldPriceText": "0,00",
        "sellingPriceText": "1.499,00",
        "buyingPriceText": "1.499,00",
        "rrpText": "1.499,00"
      },
      "images": [
        "https://cdn.dsmcdn.com/ty1601/prod/QC/20241108/14/2eb59885-ba09-3774-a97b-8d9afe10fd50/1_org_zoom.jpg",
        "https://cdn.dsmcdn.com/ty1599/prod/QC/20241108/14/d986366e-e9b4-3d53-95eb-cf012a87bd0b/1_org_zoom.jpg",
        "https://cdn.dsmcdn.com/ty1600/prod/QC/20241108/14/1c45d672-d787-30fe-8cde-8efdd9aa56da/1_org_zoom.jpg",
        "https://cdn.dsmcdn.com/ty1599/prod/QC/20241108/14/32bb6114-0d87-33cd-b276-62777f73d47d/1_org_zoom.jpg",
        "https://cdn.dsmcdn.com/ty1600/prod/QC/20241108/14/189e8616-9895-3f1d-9f84-275174932287/1_org_zoom.jpg",
        "https://cdn.dsmcdn.com/ty1599/prod/QC/20241108/14/b6951308-c648-3157-a804-9e01e10e5e21/1_org_zoom.jpg",
        "https://cdn.dsmcdn.com/ty1600/prod/QC/20241108/14/b484c8cf-af3e-30cd-9413-7a59e9aa7bab/1_org_zoom.jpg"
      ],
      "imageUrl": "https://cdn.dsmcdn.com/ty1601/prod/QC/20241108/14/2eb59885-ba09-3774-a97b-8d9afe10fd50/1_org_zoom.jpg",
      "merchantListings": [
        {
          "promotions": [
            {
              "name": "1500 TL'ye 30 TL İndirim",
              "promotionDiscountType": "DiscountOnBasket",
              "shortName": "Çok Al Az Öde",
              "id": 25747664,
              "discountType": 2,
              "isApplied": false,
              "isTyPlus": false
            },
            {
              "name": "2. Ürüne 50 TL İndirim",
              "promotionDiscountType": "TwoForOne",
              "shortName": "Çok Al Az Öde",
              "id": 25747672,
              "discountType": 2,
              "isApplied": false,
              "isTyPlus": false
            },
            {
              "name": "300 TL ve Üzeri Kargo Bedava (Satıcı Karşılar)",
              "promotionDiscountType": "Cargo",
              "shortName": "Kargo Bedava",
              "id": 23754779,
              "discountType": 7,
              "isApplied": true,
              "isTyPlus": false
            }
          ],
          "variants": [
            {
              "unitInfo": {
                "unitPrice": null,
                "typeName": null,
                "unit": null
              },
              "userSegment": null,
              "discountedPriceInfo": "",
              "listingId": "ffa39c405fa02887231536be1dfcd449",
              "barcode": "THK3000012354501213221",
              "groupTagIds": [
                "ebb03b49-5399-4c1c-902e-f2f979d1088b"
              ],
              "variantAttributes": [],
              "tagDetails": [
                {
                  "tag": "installment_pft3",
                  "displayName": "Peşin Fiyatına 3 Taksit",
                  "tagId": 4905,
                  "searchable": false,
                  "priceTagStamp": true,
                  "hasStamp": true
                }
              ],
              "price": {
                "currency": "TRY",
                "buyingPrice": 0,
                "sellingPrice": 1499,
                "originalPrice": 1499,
                "discountedPrice": 1499,
                "profitMargin": 0,
                "rrp": 0,
                "couponApplicablePrice": 1499,
                "discountedPriceAfterNoLimitPromotions": 1499,
                "tyPlusCouponApplicablePrice": 1499
              },
              "rushDeliveryDuration": 24,
              "lowestPriceDuration": {
                "duration": 0
              },
              "itemNumber": 1188809793,
              "quantity": 136,
              "sellable": true,
              "isWinner": true,
              "freeCargo": true,
              "hasCollectable": false
            }
          ],
          "stamps": [],
          "customValues": [
            {
              "key": "deliveryCountries",
              "value": "AZ"
            },
            {
              "key": "origin",
              "value": "TR"
            }
          ],
          "merchant": {
            "id": 747032
          },
          "isWinner": true,
          "freeCargo": false
        }
      ],
      "recommendedRetailPrice": null,
      "isRunningOut": false,
      "url": "/tastech/fotokapan-kamera-16mp-full-hd-1080p-gece-goruslu-2-inc-lcd-ekran-su-gecirmez-avci-doga-kamerasi-p-871121751",
      "rating": {
        "averageRating": 4.181818181818182,
        "totalComments": 11
      },
      "ratingScore": {
        "averageRating": 4.181818181818182,
        "totalCount": 11
      },
      "hasReviewPhoto": true,
      "stamps": [],
      "tagDetails": [
        {
          "tag": "installment_pft3",
          "displayName": "Peşin Fiyatına 3 Taksit",
          "tagId": 4905,
          "searchable": false,
          "priceTagStamp": true,
          "hasStamp": true
        }
      ],
      "promotions": [
        {
          "id": 25747664,
          "name": "1500 TL'ye 30 TL İndirim",
          "discountType": 2,
          "shortName": "Çok Al Az Öde",
          "promotionDiscountType": "DiscountOnBasket",
          "isTyPlus": false
        },
        {
          "id": 25747672,
          "name": "2. Ürüne 50 TL İndirim",
          "discountType": 2,
          "shortName": "Çok Al Az Öde",
          "promotionDiscountType": "TwoForOne",
          "isTyPlus": false
        },
        {
          "id": 23754779,
          "name": "300 TL ve Üzeri Kargo Bedava (Satıcı Karşılar)",
          "discountType": 7,
          "shortName": "Kargo Bedava",
          "promotionDiscountType": "Cargo",
          "isTyPlus": false
        }
      ],
      "pricePromotion": null,
      "socialProofs": [
        {
          "type": "basketCount",
          "value": "6",
          "translateKey": "socialProof_basketCount",
          "icon": "https://cdn.dsmcdn.com/mobile/search-result/Socialproof_basketcount.png"
        },
        {
          "type": "orderCountL3D",
          "value": "1",
          "translateKey": "socialProof_orderCountL365D",
          "icon": "https://cdn.dsmcdn.com/web/production/rocket-icon.png"
        },
        {
          "type": "favoriteCount",
          "value": "297",
          "translateKey": "socialProof_favoriteCount",
          "icon": "https://cdn.dsmcdn.com/web/production/orange-heart.png"
        }
      ],
      "lowestPriceDuration": 0,
      "winnerVariant": {
        "unitInfo": {
          "unitPrice": null,
          "typeName": null,
          "unit": null
        },
        "userSegment": null,
        "discountedPriceInfo": "",
        "listingId": "ffa39c405fa02887231536be1dfcd449",
        "barcode": "THK3000012354501213221",
        "groupTagIds": [
          "ebb03b49-5399-4c1c-902e-f2f979d1088b"
        ],
        "variantAttributes": [],
        "tagDetails": [
          {
            "tag": "installment_pft3",
            "displayName": "Peşin Fiyatına 3 Taksit",
            "tagId": 4905,
            "searchable": false,
            "priceTagStamp": true,
            "hasStamp": true
          }
        ],
        "price": {
          "currency": "TRY",
          "buyingPrice": 0,
          "sellingPrice": 1499,
          "originalPrice": 1499,
          "discountedPrice": 1499,
          "profitMargin": 0,
          "rrp": 0,
          "couponApplicablePrice": 1499,
          "discountedPriceAfterNoLimitPromotions": 1499,
          "tyPlusCouponApplicablePrice": 1499
        },
        "rushDeliveryDuration": 24,
        "lowestPriceDuration": {
          "duration": 0
        },
        "itemNumber": 1188809793,
        "quantity": 136,
        "sellable": true,
        "isWinner": true,
        "freeCargo": true,
        "hasCollectable": false
      },
      "priceChange": "NONE",
      "promotion": [
        {
          "id": 25747664,
          "name": "1500 TL'ye 30 TL İndirim",
          "discountType": 2,
          "shortName": "Çok Al Az Öde",
          "promotionDiscountType": "DiscountOnBasket",
          "isTyPlus": false
        }
      ],
      "isFlash": false,
      "quantityStatusBadge": {
        "quantity": null,
        "badgeType": null
      }
    },
    {
      "id": 327221289,
      "name": "Foto Kapan Vahşi Yaşam Izleme Hareket Sensörlü Kamuflaj Avcı Kamera Su Geçirmez 1080 Pks",
      "inStock": true,
      "brand": {
        "id": 1476382,
        "name": "newdaki"
      },
      "webBrand": {
        "id": 1476382,
        "name": "newdaki"
      },
      "category": {
        "id": 0,
        "name": ""
      },
      "price": {
        "originalPrice": 2431,
        "discountedPrice": 2431,
        "oldPrice": 0,
        "sellingPrice": 2431,
        "buyingPrice": 2431,
        "rrp": 2431,
        "pureRrp": 2431,
        "favoritedPrice": 0,
        "currency": "TL",
        "originalPriceText": "2.431,00",
        "discountedPriceText": "2.431,00",
        "oldPriceText": "0,00",
        "sellingPriceText": "2.431,00",
        "buyingPriceText": "2.431,00",
        "rrpText": "2.431,00"
      },
      "images": [
        "https://cdn.dsmcdn.com/ty1528/product/media/images/prod/QC/20240907/15/54de2915-f4cb-3ca2-b898-69349fcd9afc/1_org_zoom.jpg",
        "https://cdn.dsmcdn.com/ty1528/product/media/images/prod/QC/20240907/15/ee06c25e-58cb-369c-bd36-f2910caa9d63/1_org_zoom.jpg",
        "https://cdn.dsmcdn.com/ty1531/product/media/images/prod/QC/20240907/15/20cbe9d1-e5b9-3ec1-b457-6a095e752ecc/1_org_zoom.jpg",
        "https://cdn.dsmcdn.com/ty1531/product/media/images/prod/QC/20240907/15/f49e519c-e52c-3c22-a9d8-bdfec1f4dd83/1_org_zoom.jpg",
        "https://cdn.dsmcdn.com/ty1527/product/media/images/prod/QC/20240907/15/46d8e53f-f5a2-3a53-bb62-43ac797e9f5a/1_org_zoom.jpg",
        "https://cdn.dsmcdn.com/ty1531/product/media/images/prod/QC/20240907/15/d6779864-acd4-3372-ba57-e57f40d0e4fa/1_org_zoom.jpg"
      ],
      "imageUrl": "https://cdn.dsmcdn.com/ty1528/product/media/images/prod/QC/20240907/15/54de2915-f4cb-3ca2-b898-69349fcd9afc/1_org_zoom.jpg",
      "merchantListings": [
        {
          "promotions": [
            {
              "name": "300 TL ve Üzeri Kargo Bedava (Satıcı Karşılar)",
              "promotionDiscountType": "Cargo",
              "shortName": "Kargo Bedava",
              "id": 23764894,
              "discountType": 7,
              "isApplied": true,
              "isTyPlus": false
            }
          ],
          "variants": [
            {
              "unitInfo": {
                "unitPrice": null,
                "typeName": null,
                "unit": null
              },
              "userSegment": null,
              "discountedPriceInfo": "",
              "listingId": "918577084010c43df62c5734f879afe7",
              "barcode": "GLD-FTKPN",
              "groupTagIds": [],
              "variantAttributes": [],
              "tagDetails": [
                {
                  "tag": "installment_pft3",
                  "displayName": "Peşin Fiyatına 3 Taksit",
                  "tagId": 4905,
                  "searchable": false,
                  "priceTagStamp": true,
                  "hasStamp": true
                }
              ],
              "price": {
                "currency": "TRY",
                "buyingPrice": 0,
                "sellingPrice": 2431,
                "originalPrice": 2431,
                "discountedPrice": 2431,
                "profitMargin": 0,
                "rrp": 0,
                "couponApplicablePrice": 2431,
                "discountedPriceAfterNoLimitPromotions": 2431,
                "tyPlusCouponApplicablePrice": 2431
              },
              "rushDeliveryDuration": 24,
              "lowestPriceDuration": {
                "duration": 0
              },
              "itemNumber": 521217802,
              "quantity": 964,
              "sellable": true,
              "isWinner": true,
              "freeCargo": true,
              "hasCollectable": false
            }
          ],
          "stamps": [],
          "customValues": [
            {
              "key": "deliveryCountries",
              "value": "AZ"
            },
            {
              "key": "origin",
              "value": "TR"
            }
          ],
          "merchant": {
            "id": 118605
          },
          "isWinner": true,
          "freeCargo": false
        }
      ],
      "recommendedRetailPrice": null,
      "isRunningOut": false,
      "url": "/newdaki/foto-kapan-vahsi-yasam-izleme-hareket-sensorlu-kamuflaj-avci-kamera-su-gecirmez-1080-pks-p-327221289",
      "rating": {
        "averageRating": 4.5,
        "totalComments": 10
      },
      "ratingScore": {
        "averageRating": 4.5,
        "totalCount": 10
      },
      "hasReviewPhoto": true,
      "stamps": [],
      "tagDetails": [
        {
          "tag": "installment_pft3",
          "displayName": "Peşin Fiyatına 3 Taksit",
          "tagId": 4905,
          "searchable": false,
          "priceTagStamp": true,
          "hasStamp": true
        }
      ],
      "promotions": [
        {
          "id": 23764894,
          "name": "300 TL ve Üzeri Kargo Bedava (Satıcı Karşılar)",
          "discountType": 7,
          "shortName": "Kargo Bedava",
          "promotionDiscountType": "Cargo",
          "isTyPlus": false
        }
      ],
      "pricePromotion": null,
      "socialProofs": [
        {
          "type": "basketCount",
          "value": "10",
          "translateKey": "socialProof_basketCount",
          "icon": "https://cdn.dsmcdn.com/mobile/search-result/Socialproof_basketcount.png"
        },
        {
          "type": "orderCountL3D",
          "value": "1",
          "translateKey": "socialProof_orderCountL365D",
          "icon": "https://cdn.dsmcdn.com/web/production/rocket-icon.png"
        },
        {
          "type": "favoriteCount",
          "value": "194",
          "translateKey": "socialProof_favoriteCount",
          "icon": "https://cdn.dsmcdn.com/web/production/orange-heart.png"
        }
      ],
      "lowestPriceDuration": 0,
      "winnerVariant": {
        "unitInfo": {
          "unitPrice": null,
          "typeName": null,
          "unit": null
        },
        "userSegment": null,
        "discountedPriceInfo": "",
        "listingId": "918577084010c43df62c5734f879afe7",
        "barcode": "GLD-FTKPN",
        "groupTagIds": [],
        "variantAttributes": [],
        "tagDetails": [
          {
            "tag": "installment_pft3",
            "displayName": "Peşin Fiyatına 3 Taksit",
            "tagId": 4905,
            "searchable": false,
            "priceTagStamp": true,
            "hasStamp": true
          }
        ],
        "price": {
          "currency": "TRY",
          "buyingPrice": 0,
          "sellingPrice": 2431,
          "originalPrice": 2431,
          "discountedPrice": 2431,
          "profitMargin": 0,
          "rrp": 0,
          "couponApplicablePrice": 2431,
          "discountedPriceAfterNoLimitPromotions": 2431,
          "tyPlusCouponApplicablePrice": 2431
        },
        "rushDeliveryDuration": 24,
        "lowestPriceDuration": {
          "duration": 0
        },
        "itemNumber": 521217802,
        "quantity": 964,
        "sellable": true,
        "isWinner": true,
        "freeCargo": true,
        "hasCollectable": false
      },
      "priceChange": "NONE",
      "promotion": [
        {
          "id": 23764894,
          "name": "300 TL ve Üzeri Kargo Bedava (Satıcı Karşılar)",
          "discountType": 7,
          "shortName": "Kargo Bedava",
          "promotionDiscountType": "Cargo",
          "isTyPlus": false
        }
      ],
      "isFlash": false,
      "quantityStatusBadge": {
        "quantity": null,
        "badgeType": null
      }
    },
    {
      "id": 1075535288,
      "name": "X60P Live Max 48 Mp Gsm Destekli Fotokapan",
      "inStock": true,
      "brand": {
        "id": 2791215,
        "name": "GardePro"
      },
      "webBrand": {
        "id": 2791215,
        "name": "GardePro"
      },
      "category": {
        "id": 0,
        "name": ""
      },
      "price": {
        "originalPrice": 12700,
        "discountedPrice": 12700,
        "oldPrice": 0,
        "sellingPrice": 12700,
        "buyingPrice": 12700,
        "rrp": 12700,
        "pureRrp": 12700,
        "favoritedPrice": 0,
        "currency": "TL",
        "originalPriceText": "12.700,00",
        "discountedPriceText": "12.700,00",
        "oldPriceText": "0,00",
        "sellingPriceText": "12.700,00",
        "buyingPriceText": "12.700,00",
        "rrpText": "12.700,00"
      },
      "images": [
        "https://cdn.dsmcdn.com/ty1805/prod/QC_PREP/20251224/11/41a854c8-13d6-3ecd-8626-3fd39315720b/1_org_zoom.jpg",
        "https://cdn.dsmcdn.com/ty1803/prod/QC_PREP/20251224/11/2c239b73-7c46-34bd-9580-761e59e66469/1_org_zoom.jpg",
        "https://cdn.dsmcdn.com/ty1805/prod/QC_PREP/20251224/11/68ab0c36-398d-3de9-b37c-5b195f5588e2/1_org_zoom.jpg",
        "https://cdn.dsmcdn.com/ty1803/prod/QC_PREP/20251224/11/97ed3809-b769-3c49-9c96-680582ad459c/1_org_zoom.jpg",
        "https://cdn.dsmcdn.com/ty1803/prod/QC_PREP/20251224/11/9ea1d784-1619-3a10-a605-a7f409b6ebc7/1_org_zoom.jpg",
        "https://cdn.dsmcdn.com/ty1803/prod/QC_PREP/20251224/11/1d4380ff-048c-3d42-aa33-7f6e380c4fbc/1_org_zoom.jpg",
        "https://cdn.dsmcdn.com/ty1803/prod/QC_PREP/20251224/11/6d503774-847c-399c-a122-7fdf0b90f2b3/1_org_zoom.jpg"
      ],
      "imageUrl": "https://cdn.dsmcdn.com/ty1805/prod/QC_PREP/20251224/11/41a854c8-13d6-3ecd-8626-3fd39315720b/1_org_zoom.jpg",
      "merchantListings": [
        {
          "promotions": [
            {
              "name": "300 TL ve Üzeri Kargo Bedava (Satıcı Karşılar)",
              "promotionDiscountType": "Cargo",
              "shortName": "Kargo Bedava",
              "id": 25010940,
              "discountType": 7,
              "isApplied": true,
              "isTyPlus": false
            }
          ],
          "variants": [
            {
              "unitInfo": {
                "unitPrice": null,
                "typeName": null,
                "unit": null
              },
              "userSegment": null,
              "discountedPriceInfo": "",
              "listingId": "679c44abd5a72c5e1d1a805e89afb33a",
              "barcode": "GRDPR2001",
              "groupTagIds": [],
              "variantAttributes": [],
              "tagDetails": [
                {
                  "tag": "installment_pft3",
                  "displayName": "Peşin Fiyatına 3 Taksit",
                  "tagId": 4905,
                  "searchable": false,
                  "priceTagStamp": true,
                  "hasStamp": true
                }
              ],
              "price": {
                "currency": "TRY",
                "buyingPrice": 0,
                "sellingPrice": 12700,
                "originalPrice": 12700,
                "discountedPrice": 12700,
                "profitMargin": 0,
                "rrp": 0,
                "couponApplicablePrice": 12700,
                "discountedPriceAfterNoLimitPromotions": 12700,
                "tyPlusCouponApplicablePrice": 12700
              },
              "rushDeliveryDuration": 0,
              "lowestPriceDuration": {
                "duration": 0
              },
              "itemNumber": 1485969247,
              "quantity": 4,
              "sellable": true,
              "isWinner": true,
              "freeCargo": true,
              "hasCollectable": false
            }
          ],
          "stamps": [],
          "merchant": {
            "id": 1152764
          },
          "isWinner": true,
          "freeCargo": false
        }
      ],
      "recommendedRetailPrice": null,
      "isRunningOut": false,
      "url": "/gardepro/x60p-live-max-48-mp-gsm-destekli-fotokapan-p-1075535288",
      "rating": {
        "averageRating": 0,
        "totalComments": 0
      },
      "ratingScore": {
        "averageRating": 0,
        "totalCount": 0
      },
      "hasReviewPhoto": false,
      "stamps": [],
      "tagDetails": [
        {
          "tag": "installment_pft3",
          "displayName": "Peşin Fiyatına 3 Taksit",
          "tagId": 4905,
          "searchable": false,
          "priceTagStamp": true,
          "hasStamp": true
        }
      ],
      "promotions": [
        {
          "id": 25010940,
          "name": "300 TL ve Üzeri Kargo Bedava (Satıcı Karşılar)",
          "discountType": 7,
          "shortName": "Kargo Bedava",
          "promotionDiscountType": "Cargo",
          "isTyPlus": false
        }
      ],
      "pricePromotion": null,
      "socialProofs": [
        {
          "type": "orderCountL3D",
          "value": "1",
          "translateKey": "socialProof_orderCountL365D",
          "icon": "https://cdn.dsmcdn.com/web/production/rocket-icon.png"
        }
      ],
      "lowestPriceDuration": 0,
      "winnerVariant": {
        "unitInfo": {
          "unitPrice": null,
          "typeName": null,
          "unit": null
        },
        "userSegment": null,
        "discountedPriceInfo": "",
        "listingId": "679c44abd5a72c5e1d1a805e89afb33a",
        "barcode": "GRDPR2001",
        "groupTagIds": [],
        "variantAttributes": [],
        "tagDetails": [
          {
            "tag": "installment_pft3",
            "displayName": "Peşin Fiyatına 3 Taksit",
            "tagId": 4905,
            "searchable": false,
            "priceTagStamp": true,
            "hasStamp": true
          }
        ],
        "price": {
          "currency": "TRY",
          "buyingPrice": 0,
          "sellingPrice": 12700,
          "originalPrice": 12700,
          "discountedPrice": 12700,
          "profitMargin": 0,
          "rrp": 0,
          "couponApplicablePrice": 12700,
          "discountedPriceAfterNoLimitPromotions": 12700,
          "tyPlusCouponApplicablePrice": 12700
        },
        "rushDeliveryDuration": 0,
        "lowestPriceDuration": {
          "duration": 0
        },
        "itemNumber": 1485969247,
        "quantity": 4,
        "sellable": true,
        "isWinner": true,
        "freeCargo": true,
        "hasCollectable": false
      },
      "priceChange": "NONE",
      "promotion": [
        {
          "id": 25010940,
          "name": "300 TL ve Üzeri Kargo Bedava (Satıcı Karşılar)",
          "discountType": 7,
          "shortName": "Kargo Bedava",
          "promotionDiscountType": "Cargo",
          "isTyPlus": false
        }
      ],
      "isFlash": false,
      "quantityStatusBadge": {
        "quantity": null,
        "badgeType": "RUNNING_OUT"
      }
    }
  ]
}